{
  "account": {
    "id": "1403881130802225152",
    "screen_name": "BTCdayu",
    "name": "大宇",
    "description": "宝典 https://t.co/EIMVhaCHyk\n\n💰省手续费注册\n币安 https://t.co/CLh8KEA9Ri\nOK \n交易所 https://t.co/k9RDrZX7l7\n钱包 https://t.co/0GUmXMTC19\n\n✈️投资频道\nhttps://t.co/f4KWsBAJpr\n\n🚫警告\n只有BTC可长拿，其他任何币种都只能短炒，长拿终将归零‼️",
    "profile_image_url": "https://pbs.twimg.com/profile_images/1862767252400967680/mjEMe7kp_normal.jpg",
    "profile_banner_url": "https://pbs.twimg.com/profile_banners/1403881130802225152/1739255404",
    "followers_count": 279764,
    "friends_count": 3765,
    "statuses_count": 18588,
    "favourites_count": 4336,
    "listed_count": 4423,
    "location": "收费群1688U/年，点链接",
    "website": "https://t.co/ezDy9BKvqc",
    "birthdate": null,
    "verified_type": null,
    "is_blue_verified": true,
    "following": true,
    "followed_by": null,
    "can_dm": true,
    "protected": false,
    "created_at": "2021-06-13 09:05:28 +08:00",
    "url": "https://twitter.com/BTCdayu",
    "rest_id": "1403881130802225152"
  },
  "tweets": [
    {
      "id": "1597415699109990402#m",
      "content": "币圈必备网址及神级工具（极简版），大家记得收藏转发。\n\n网址：dayu.xyz 随时访问。\n\n投资指南、工具教程、研究报告，一网打尽。",
      "timestamp": "Nov 29, 2022 · 2:22 AM UTC",
      "url": "https://twitter.com/BTCdayu/status/1597415699109990402#m",
      "author": "BTCdayu"
    },
    {
      "id": "1980423916020764910#m",
      "content": "BASE链前几天抨击币安，有人和Jessie讲了下SOL被卡脖子的事之后，Jessie大惊，连夜开始学中文，并称币安人生是个好东西，表示自己在过BASE人生。\n\n那边也立即吩咐管家：快上线BNB，以后我们的好上他们！\n\nCZ抚须微笑，如此东西方大团结，才是吾辈之愿耳。\n\n从此，BASE和BSC链的人，都过上了好的人生。",
      "timestamp": "Oct 21, 2025 · 12:00 AM UTC",
      "url": "https://twitter.com/BTCdayu/status/1980423916020764910#m",
      "author": "BTCdayu"
    },
    {
      "id": "1980418346228342898#m",
      "content": "+1",
      "timestamp": "Oct 20, 2025 · 11:38 PM UTC",
      "url": "https://twitter.com/BTCdayu/status/1980418346228342898#m",
      "author": "BTCdayu"
    },
    {
      "id": "1980132888462102674#m",
      "content": "iphone 17 air真的好漂亮，好薄，好喜欢\n就是屏幕护眼还不够好",
      "timestamp": "Oct 20, 2025 · 4:44 AM UTC",
      "url": "https://twitter.com/BTCdayu/status/1980132888462102674#m",
      "author": "BTCdayu"
    },
    {
      "id": "1979880744077111407#m",
      "content": "神：马斯克、黄仁勋、段永平、乔布斯\n\nS级：巴菲特、李嘉诚、马化腾、王宁、黄铮\n\nA级：盖茨、扎克伯格、马云、任正非、雷军、蒋凡\n\nB级：郭台铭、王传福、曾毓群、李想\n\nC级：500强公司中的某些\n\nZ级：我",
      "timestamp": "Oct 19, 2025 · 12:02 PM UTC",
      "url": "https://twitter.com/BTCdayu/status/1979880744077111407#m",
      "author": "BTCdayu"
    },
    {
      "id": "1979735181083947516#m",
      "content": "桥水基金创始人达里欧认为：\n黄金是“永恒且普世”货币形式，是唯一不依赖对手方信用的资产，投资者应将投资组合中高达15%的资金配置给黄金\n\n希望比特币争口气，要不然总有一种在搞龙二的羞耻感，还是超过黄金吧……",
      "timestamp": "Oct 19, 2025 · 2:23 AM UTC",
      "url": "https://twitter.com/BTCdayu/status/1979735181083947516#m",
      "author": "BTCdayu"
    },
    {
      "id": "1979718082412335346#m",
      "content": "我跟着我的直觉和好奇心走，遇到了很多东西，此后被证明是无价之宝。”   [乔布斯在斯坦福演讲]\n\n直觉不断被修正的过程就是自我提升的过程。直觉会带领我们走向新的研究领域。[杨振宁在中科大演讲]",
      "timestamp": "Oct 19, 2025 · 1:15 AM UTC",
      "url": "https://twitter.com/BTCdayu/status/1979718082412335346#m",
      "author": "BTCdayu"
    },
    {
      "id": "1979715101491089690#m",
      "content": "一方面币圈95%以上都是空气币，被人看扁合理。\n\n另一方面，觉得币圈人都是会“过两年打成原形的赌徒”，这话背后透露出来的固步自封的落后，我得说一声，过几年，我这样的币圈菜鸟也能打得他找不到牙。相信我。",
      "timestamp": "Oct 19, 2025 · 1:03 AM UTC",
      "url": "https://twitter.com/BTCdayu/status/1979715101491089690#m",
      "author": "BTCdayu"
    },
    {
      "id": "1979713591931809815#m",
      "content": "《杨振宁谈直觉——宇宙深处的真理》\n\n一代大师杨振宁先生作古，作为这个颗蔚蓝星球上最伟大的物理学家，他关于“直觉”的论述让人读起来颇有一种大音希声的震撼感，也原文整理分享给大家（权威来源链接等附后）。\n\n我一生的体会是，直觉是在反复训练之后自然形成的。它不是天生的灵感，而是一种经验升华后的思维模式。\n\n每一个人都有很多直觉，而直觉有许多是需要修正的。\n\n直觉不断被修正的过程就是自我提升的过程，直觉会带领我们走向新的研究领域。\n\n直觉与书本知识冲突时，是最好的学习机会。\n\n人类的理性是有限的，我们的直觉或许能接近那个更深的秩序。那秩序是什么，我不敢说，但我愿意称它为造物的美。\n\n科学的真正进步，不在于你知道了多少事实，而在于你看问题的方式、你的直觉是否变得更正确。\n\n理论物理的发展，靠的不是记忆，而是直觉。直觉的培养比知识更难。\n\n物理学家的真正创造来自于对自然的深刻直觉，而非复杂计算。\n\n直觉不是凭空的，它是在大量阅读、实验和思考之后，内心自然生出的方向感。\n\n一个研究者在开始时像盲人摸象，摸多了以后，就会慢慢形成图像。这图像就是直觉。\n\n那一刻我不能证明它，只是直觉告诉我，物理世界不能那么对称。\n\n以下为一些来源与文章，也值得学习一下。\n杨振宁电子科大演讲 《直觉会带领我们走向新的研究领域》\ncas.cn/ys/gzdt/201009/t20100…\n\n杨振宁（清华大学演讲）《我的学习与研究经历》\nzhuanlan.zhihu.com/p/4331570…\n\n杨振宁国科大演讲全文\nnews.ucas.ac.cn/cmjj/d39d6bb…\n\n杨振宁：美在科学与艺术中的异同\nrufanzhang-group.cn/sys-nd/9…\n\n数学或理论物理美的直觉感受\nnews.qq.com/rain/a/20240713A…\n\n【视频片断】杨振宁：直觉很重要，但要不断被思考\nbilibili.com/video/BV1Zw411x…",
      "timestamp": "Oct 19, 2025 · 12:57 AM UTC",
      "url": "https://twitter.com/BTCdayu/status/1979713591931809815#m",
      "author": "BTCdayu"
    },
    {
      "id": "1979706085398438275#m",
      "content": "以前我看有一些高人写的人生原则：不借钱\n其实不是特别懂，但当自己多经历各种事以后，也觉得这三个字是特别有哲理的人。\n\n值得帮的人往往不需要走到这一步\n不值得帮的人会不断走到这一步\n\n这也是性格决定命运。",
      "timestamp": "Oct 19, 2025 · 12:28 AM UTC",
      "url": "https://twitter.com/BTCdayu/status/1979706085398438275#m",
      "author": "BTCdayu"
    },
    {
      "id": "1979704946892447843#m",
      "content": "论上当受骗这件事，以前我是第一，以后可能要称第二了。善良的人总是难免被骗，不过这种事情确实是十分受伤。\n\n我在上当受骗多了以后，渐渐地从命运角度给了自己一些规则，比如“干涉他人命运要慎重，干涉就是背负因果”。\n\n命理之中，有“出门遇贵人”的说法，命理中有不同的各种贵人，福星贵人、天乙贵人、太极贵人等等，但是并不是每个遇到他们的人都能得福，所谓“命薄则无福消受”，这些都是玄学的东西，但如果用科学角度来解释，其实是“性格决定命运”，不同性格的人，难以相融，因为不是相生，而是相克。\n\n如果一个人一心向善，而另一个人则是满心诡计，善良的人受到的伤害是随着相处而不断加深，而且可能在因果暴发的那一刻才最终暴发出来。\n\n不过，善良的人也最能识别善良，在向宇宙释放能量场时，也会受到更多回应，这些回应其实就让路越走越宽的原因。",
      "timestamp": "Oct 19, 2025 · 12:23 AM UTC",
      "url": "https://twitter.com/BTCdayu/status/1979704946892447843#m",
      "author": "BTCdayu"
    },
    {
      "id": "1979579985796174039#m",
      "content": "“真正的进步不是你记住了多少知识，而是你直觉发生的变化。”\n                            ——杨振宁",
      "timestamp": "Oct 18, 2025 · 4:07 PM UTC",
      "url": "https://twitter.com/BTCdayu/status/1979579985796174039#m",
      "author": "BTCdayu"
    },
    {
      "id": "1979576238537867767#m",
      "content": "在推特3年，看过的最经典的话前三\n\n这能解释很多事情。\n#投资备忘",
      "timestamp": "Oct 18, 2025 · 3:52 PM UTC",
      "url": "https://twitter.com/BTCdayu/status/1979576238537867767#m",
      "author": "BTCdayu"
    },
    {
      "id": "1979514070371033570#m",
      "content": "仓位比观点更有力。\n你现在在币圈的资产中，持仓的币和U比例是多少？",
      "timestamp": "Oct 18, 2025 · 11:45 AM UTC",
      "url": "https://twitter.com/BTCdayu/status/1979514070371033570#m",
      "author": "BTCdayu"
    },
    {
      "id": "1979513721732186545#m",
      "content": "看了一圈，接下来行情主要有三种观点，哪一种概率大？\n\n1、当前为熊市初期\n在降息和总统周期在美股崩盘中进入熊市，可能反抽12万确认，也可能震荡后直接走坏跌破10万\n\n2、当前为牛回头\n极限位置在7.5-8.5万支撑，并获得冲击15万的力量\n\n3、当前已到底\n恐惧指数20以下，抄就完了，随时大反弹",
      "timestamp": "Oct 18, 2025 · 11:43 AM UTC",
      "url": "https://twitter.com/BTCdayu/status/1979513721732186545#m",
      "author": "BTCdayu"
    },
    {
      "id": "1979439230561738805#m",
      "content": "看看有人能猜到图上这个币是什么不，以前巅峰时谁说它不好，能被喷死。",
      "timestamp": "Oct 18, 2025 · 6:47 AM UTC",
      "url": "https://twitter.com/BTCdayu/status/1979439230561738805#m",
      "author": "BTCdayu"
    },
    {
      "id": "1979438869176332714#m",
      "content": "MEME币给散户一个赌博机会，明知是空气，则愿赌服输。\n\n但币圈90%山寨币，伪装成价值项目，高大上的背书、高额的融资、专业收割的做市商、利益输送上所一条龙，韭菜被迷得不要不要的，套住了往往心存侥幸，现货能亏90%。\n\n下图这个，专套基本面研究者和盲信韭菜，现在没人提了，这种到处都是。",
      "timestamp": "Oct 18, 2025 · 6:46 AM UTC",
      "url": "https://twitter.com/BTCdayu/status/1979438869176332714#m",
      "author": "BTCdayu"
    },
    {
      "id": "1979361888615141512#m",
      "content": "为什么币圈有那么多的空气币？垃圾币？\n\n本质还是用户教育不够，95%的人仍然是在瞎买，哪个拉盘就买一点，那项目方割起来也很方便——而且这些买了的人还容易幻想，套住了还乖乖等着解套，就像绵羊一样。\n\n币圈除了几个大币，只有少数有收入，而且收入要强赋能币价的项目才值得关注，其他都归零吧，拜托",
      "timestamp": "Oct 18, 2025 · 1:40 AM UTC",
      "url": "https://twitter.com/BTCdayu/status/1979361888615141512#m",
      "author": "BTCdayu"
    },
    {
      "id": "1979361381758702060#m",
      "content": "NFT项目发空投，已经麻木\n当然\n其实也厌倦了币圈99%的空气币",
      "timestamp": "Oct 18, 2025 · 1:38 AM UTC",
      "url": "https://twitter.com/BTCdayu/status/1979361381758702060#m",
      "author": "BTCdayu"
    },
    {
      "id": "1979078992176316729#m",
      "content": "今天大跌，她和我分手了。\n\n在把我房门摔坏的10秒前，她回头嘲笑我：还说什么币圈赚钱，不如我买的黄金涨得多，呵呵？\n\n正要辩解，BTC又跌了！泪水模糊了双眼，我飞起一脚，将前前任留给我的电饭煲当场踢飞：狗庄，爱情都被你搞爆仓！\n\n等BTC 100W，你们会后悔的，小红、小玉、小春、小梅、小刘。",
      "timestamp": "Oct 17, 2025 · 6:56 AM UTC",
      "url": "https://twitter.com/BTCdayu/status/1979078992176316729#m",
      "author": "BTCdayu"
    },
    {
      "id": "1979072070232457378#m",
      "content": "目前币圈人群分几类：\n\n1、等币安上MEME现货派\n2、空仓/轻仓在等熊市，准备抄把大的\n3、重仓在等利好拉到15-20万的\n4、我这种写段子的",
      "timestamp": "Oct 17, 2025 · 6:28 AM UTC",
      "url": "https://twitter.com/BTCdayu/status/1979072070232457378#m",
      "author": "BTCdayu"
    },
    {
      "id": "1979040618031779999#m",
      "content": "大家要注意，网上现在有好些说是我的地址在炒MEME币，尤其是中文名币，均是假的，我已经在多天前清仓MEME币。\n\n我的风格也基本上不买这些链上的小币、新币。\n最近的三波赚大钱，都是上ALPHA之后第一时间出手，币安人生、4、PALU，而且涨不动就走了。\n\n我对MEME没有什么幻想，也不擅长早期对P，赚个1-5倍就行",
      "timestamp": "Oct 17, 2025 · 4:23 AM UTC",
      "url": "https://twitter.com/BTCdayu/status/1979040618031779999#m",
      "author": "BTCdayu"
    },
    {
      "id": "1979037799845093756#m",
      "content": "现在币安上不少小币，前几天暴砸后，竟然也就直接在原地躺下了，没有再涨回去。\n\n说明：\n一是散户再便宜也不买了。\n二是做市商也不买了。\n\n看起来，只有韭菜还在回味与留恋。",
      "timestamp": "Oct 17, 2025 · 4:12 AM UTC",
      "url": "https://twitter.com/BTCdayu/status/1979037799845093756#m",
      "author": "BTCdayu"
    },
    {
      "id": "1978842112142590376#m",
      "content": "可还有人记得，上轮熊市那一路下跌的400天，和犹疑中慢慢回到前高的650天么……",
      "timestamp": "Oct 16, 2025 · 3:14 PM UTC",
      "url": "https://twitter.com/BTCdayu/status/1978842112142590376#m",
      "author": "BTCdayu"
    },
    {
      "id": "1978830330409726343#m",
      "content": "时代的眼泪，当时想要整理钱包，但GAS费太高，一直没动，听了傻哥的，也整理了一下，还算有惊喜。\n\n当年买的夸克、电子啥的，当时说“即使跌没了只要BTC涨到多少就回本”，果然也U本位回本了……\n\n玩过铭文的推荐都用UNISAT钱包检查一下，有余额就直接发送到币安就行了。",
      "timestamp": "Oct 16, 2025 · 2:28 PM UTC",
      "url": "https://twitter.com/BTCdayu/status/1978830330409726343#m",
      "author": "BTCdayu"
    },
    {
      "id": "1978475537728487746#m",
      "content": "曾经的明星项目，自发币起好像一直在在出货、出货、出货、出货……\n\n中间所有胆敢相信这种币的人，应该都过上了自己不想要的人生了。",
      "timestamp": "Oct 15, 2025 · 2:58 PM UTC",
      "url": "https://twitter.com/BTCdayu/status/1978475537728487746#m",
      "author": "BTCdayu"
    },
    {
      "id": "1978472766920884427#m",
      "content": "感谢大A",
      "timestamp": "Oct 15, 2025 · 2:47 PM UTC",
      "url": "https://twitter.com/BTCdayu/status/1978472766920884427#m",
      "author": "BTCdayu"
    },
    {
      "id": "1978393358805446807#m",
      "content": "突然发现自己一直以来的动力来自哪里，准确的说主要的动力源。\n\n主要是来自对完成命运挑战、变得更加强大的渴望，这是关于过程的乐趣。\n\n而对这个世界了解得越多，对厉害的人了解越多，越觉得自己的渺小脆弱和无知，因此，一个伪灵根而且没有小绿瓶，想要变强，自然就会有持续的自生动力。",
      "timestamp": "Oct 15, 2025 · 9:31 AM UTC",
      "url": "https://twitter.com/BTCdayu/status/1978393358805446807#m",
      "author": "BTCdayu"
    },
    {
      "id": "1978019601288933606#m",
      "content": "在上一轮熊市开始，最典型的症状就是神仙打架，标志性信号就是做市商暴雷，当前还没有看到任何暴雷事件，希望一切安好。\n\n我的仓位在这么被轰炸，我的电瓶车要跑到冒烟了。",
      "timestamp": "Oct 14, 2025 · 8:46 AM UTC",
      "url": "https://twitter.com/BTCdayu/status/1978019601288933606#m",
      "author": "BTCdayu"
    },
    {
      "id": "1977988437107249203#m",
      "content": "索拉拉\n带有口音的中文名……\n\n我刚刚买进去10个索拉拉，怎么一下子就跌没了，现在只有0.01个索拉拉，现在怎么办？",
      "timestamp": "Oct 14, 2025 · 6:42 AM UTC",
      "url": "https://twitter.com/BTCdayu/status/1977988437107249203#m",
      "author": "BTCdayu"
    },
    {
      "id": "1977967041140367636#m",
      "content": "个人签名加了一句话\n\n🚫警告 \n只有BTC可长拿，其他任何币种都只能短炒，长拿终将归零‼️\n\n币圈，最好的MEME币也可能就涨几天，之后就是归零。而99%的VC币最后也是归零，很怕新手追着问：XX山寨能长拿吗？\n\n凡是要问别人时，就反着来。\n问别人能买吗？别买!\n要卖吗？卖!\n能抄底吗？不能！",
      "timestamp": "Oct 14, 2025 · 5:17 AM UTC",
      "url": "https://twitter.com/BTCdayu/status/1977967041140367636#m",
      "author": "BTCdayu"
    },
    {
      "id": "1977947991333122526#m",
      "content": "清仓了所有MEME\n减仓了大多数山寨\n留好了BTC\n战战兢兢地苟着",
      "timestamp": "Oct 14, 2025 · 4:02 AM UTC",
      "url": "https://twitter.com/BTCdayu/status/1977947991333122526#m",
      "author": "BTCdayu"
    },
    {
      "id": "1977716637005656432#m",
      "content": "世界太大，机会太多\n不同时间级别对应不同的机会\n10分钟、4小时、天、月、年、十年。\n\n大千世界，禁地探宝，挑战危险极多，但机会亦多\n“请宝贝转身”。",
      "timestamp": "Oct 13, 2025 · 12:42 PM UTC",
      "url": "https://twitter.com/BTCdayu/status/1977716637005656432#m",
      "author": "BTCdayu"
    },
    {
      "id": "1977647034153975983#m",
      "content": "人们卖掉陈年老币  $SOL\n喜气洋洋买入时髦的 $BNB\n\n就像之前卖掉更老的 $ETH 买入 $SOL 那样",
      "timestamp": "Oct 13, 2025 · 8:06 AM UTC",
      "url": "https://twitter.com/BTCdayu/status/1977647034153975983#m",
      "author": "BTCdayu"
    },
    {
      "id": "1977644885483413833#m",
      "content": "下一步，监管的问题可能放松\n即使不放松也有很多“变通之道”\n下一个10年，是链上战争，各家都要亲自下场\n没有任何一个大傀儡术能击败来自大BOSS 杰夫。",
      "timestamp": "Oct 13, 2025 · 7:57 AM UTC",
      "url": "https://twitter.com/BTCdayu/status/1977644885483413833#m",
      "author": "BTCdayu"
    },
    {
      "id": "1977644199920185653#m",
      "content": "最近在想三个问题：\n未来假设链上会比CEX更大，币安把ASTER推到前面自己不下场，是否能赢得这场战斗？\n\n币安是否愿意接受可能输掉这场新的10年战争？\n\n一姐和CZ 95%的资产都是BNB，ASTER做得再大，对BNB是否有直接助力？\n\n万事不决 $BNB ！\n——写到这里，想起200多的BNB，泪水打湿了我的电瓶车",
      "timestamp": "Oct 13, 2025 · 7:54 AM UTC",
      "url": "https://twitter.com/BTCdayu/status/1977644199920185653#m",
      "author": "BTCdayu"
    },
    {
      "id": "1977640837564834149#m",
      "content": "在B站看了《凡人修仙传》之后，觉得怎么拍这么好。\n然后经群友推荐看了《牧神记》，我的天，好牛\n马上找背后制作方是否上市，一查，今年上市，连涨几个月了\n\n怎么A股就一点价值洼地都没有是吧……😩",
      "timestamp": "Oct 13, 2025 · 7:41 AM UTC",
      "url": "https://twitter.com/BTCdayu/status/1977640837564834149#m",
      "author": "BTCdayu"
    },
    {
      "id": "1977636581088571804#m",
      "content": "投资就是投人\n\n王宁开格子铺时，麦刚普说他会成为新消费第一人；影石的创始人大学毕业啥也没有，投资人觉得他牛B投了200万；马斯克哭着到处求人差点倒掉，直到有人觉得牛逼。\n\n看长远，不是看现在做了什么、有什么，而是未来有什么。我不懂这一点而错过了很多好标的。\n\n“研究”是最大的绊脚石。",
      "timestamp": "Oct 13, 2025 · 7:24 AM UTC",
      "url": "https://twitter.com/BTCdayu/status/1977636581088571804#m",
      "author": "BTCdayu"
    },
    {
      "id": "1977614125883851079#m",
      "content": "币安的能量几乎等于大半个币圈，而且掌握了用户、流动性这两大顶层规则，有了这两个，做什么都无敌。\n\n现在MEME收归BSC，SOL很难翻身。下一步应该会是原生PREP DEX，甚至预测市场。\n\n原来觉得合规之类会不会不做，但链上DEX出来了，其他应该也一样。\n\n巨头动作慢，但动起来，攻击力就很强",
      "timestamp": "Oct 13, 2025 · 5:55 AM UTC",
      "url": "https://twitter.com/BTCdayu/status/1977614125883851079#m",
      "author": "BTCdayu"
    },
    {
      "id": "1977612033060421924#m",
      "content": "突然意识到，HYPE之后的链上永续战争才刚刚开始。\n目前没有任何迹象币安会开发一个原生的DEX，但从商业角度，我认为一定会自己做一个。\n\nASTER和BSC链上其他PREP DEX都是生态的一部分，但毕竟不是币安自己的，一姐和CZ也不参与决策，更不直接赋能BNB。\n\n币安不会什么都做，但是交易这件事不做不行？",
      "timestamp": "Oct 13, 2025 · 5:47 AM UTC",
      "url": "https://twitter.com/BTCdayu/status/1977612033060421924#m",
      "author": "BTCdayu"
    },
    {
      "id": "1977608828305961294#m",
      "content": "现在打开币安钱包，再点击现在交易，就直接进入了Meme rush页面，这个页面和同为链上工具的AXIOM的主要区别是，对方多了一个永续合约功能，底层用的是HYPE的。\n\n未来币安钱包内置永续合约好像是很必要也很自然的事，不再会是OKX那样访问第三方DAPP的方式。\n\n看起来，大概率是自研而不会用ASTER。",
      "timestamp": "Oct 13, 2025 · 5:34 AM UTC",
      "url": "https://twitter.com/BTCdayu/status/1977608828305961294#m",
      "author": "BTCdayu"
    },
    {
      "id": "1977603889194250471#m",
      "content": "ASTER好像并不会赋能BNB？那么，币安是否会在币安钱包中直接再上一个链上的合约功能？毕竟现在钱包已经直接无缝和交易所划转了，再上一个合约非常自然。\n\n但这个设想有点脑洞大开了，好像还没有人这么讨论。",
      "timestamp": "Oct 13, 2025 · 5:14 AM UTC",
      "url": "https://twitter.com/BTCdayu/status/1977603889194250471#m",
      "author": "BTCdayu"
    },
    {
      "id": "1977392761276977526#m",
      "content": "现在币安系MEME中，只有修仙和PALU应该是只有我这样的小散户在玩，半个狗庄都找不着\n\n但i人就只能玩玩这种，毕竟0社交。",
      "timestamp": "Oct 12, 2025 · 3:15 PM UTC",
      "url": "https://twitter.com/BTCdayu/status/1977392761276977526#m",
      "author": "BTCdayu"
    },
    {
      "id": "1977283469316411696#m",
      "content": "CZ和一姐主要资产都是BNB\nCZ的资产中98.5%是BNB\n这样来看，整个币安生态都是利好BNB\n\n徐总持有OKB应该没有BTC多，这可能也是两所在赋能上的差别之一\n\n下次熊市，我希望BNB能再给我一次机会",
      "timestamp": "Oct 12, 2025 · 8:01 AM UTC",
      "url": "https://twitter.com/BTCdayu/status/1977283469316411696#m",
      "author": "BTCdayu"
    },
    {
      "id": "1975983132567535816#m",
      "content": "无监管时代需要自监管，为有源头活水来\n\n币安人生，欧易人生充斥着整个推特，无数的造富神话让社区用户们激情澎湃，行业又进入了一种快钱模式。\nAlpha的成功背后是326个上线的项目仅有不到10%只有32个项目上线spot，这意味着这一年90%上线alpha的项目最后都变成了平台燃料。在没有监管的行业，交易所话语权强，并且主导性高，项目的失败似乎和交易所也没什么必然的联系，只是缺乏监管的行业如果平台不能更好的自监管，那相当于给整个行业上了猛药，流动性的成功和溃败都是在一瞬间，造富神话快速闪现，快速陨落。\n\nHyperliquid借助着链上币安的概念大获成功，Aster通过再造交易量，分得Perpdex市场的份额，似乎整个行业都在向着去中心化和更有前景的方向迈进，但是事实上呢，期货和衍生品一直以来是这个行业交易所盈利能力最强的工具，无数交易所用尽各种方法让平台的用户开始用他们的Perp产品，但是期货衍生品其实是一个零和博弈的游戏，散户在这个市场可以用数十倍到上百倍杠杆放大收益和亏损，因此强如Hyperliquid和Aster的疯狂补贴，让过去从来不玩衍生品和期货的用户开始上手期货，借助着刷取空投，大量从来没有做过杠杆交易的人疯狂入市，哪怕最终用户转化率只有10%，那这些用户在这个周期的后面六个月也很可能染上期货的赌瘾无法自拔。PerpDex特别好，但是过度的激励和干预来让更多人成为期货赌徒，这个事情就丧失了初衷，未来也容易被反噬。\n\n加密行业特别是交易所之间的竞争和博弈应该倡导什么价值观优先？许多交易所控制了资金流动性和平台流量，所以开启meme造富神话可以更好的得到领先段位，让无数人为之趋之若鹜。竞争一定是残酷的，但是在一个缺乏监管的行业中，作为业内领先者是否应该长足考虑重新思考为行业建立一套什么样的赛马机制，引领一种什么风向的散户投资浪潮。作为加密从业者，我们见证了过去几个周期泡沫的起落，也看到了DeFi/稳定币/基础设施的成熟，头部玩家如果可以想办法发力一些长远的价值赛道，做更多难而正确且长期的事情，多年之后无数的行业从业者都将之奉为推动力量和被铭记人士。\n\n我们在特朗普的周期内加密行业无数利好并且监管无限宽松，但是就是这样的无监管时代更加要求一些顶级创业者的行业责任心，帮助这个行业在这个周期取得更多突破，吸引更多更强大的创业者加入，让加密行业出现无数比肩字节跳动/拼多多这样的公司。我呼吁交易所的竞争在内部的项目创新和流量流动性方面，应该更为克制并且需要多问自己一个问题，目前做的事情三年五年之后在行业还有什么价值吗？最优秀的创业者，往往不止着眼于眼前，他们在一起创造加密行业更广阔的未来。\n\nTips：当然对很多人很难拒绝这样扑面而来的赚钱机会，并且无数快速造富的神话让每个人向往，但是请记住投资有三个原则：保住不死之身，在无数的机会中尽量少参与和少亏钱，在自己的专业领域中或者擅长方向中下大注赚大钱（有感于和巫师新加坡交流）",
      "timestamp": "Oct 8, 2025 · 5:54 PM UTC",
      "url": "https://twitter.com/BTCdayu/status/1975983132567535816#m",
      "author": "BTCdayu"
    },
    {
      "id": "1977194796071694341#m",
      "content": "312  爆仓 50亿美元，之后走牛\n\n519 爆仓80亿美元，2个月后大反弹然后走熊\n\nFTX 爆仓 100亿美元，确认熊市\n\n本次 爆仓 200亿美元\n\n走牛还是走熊？",
      "timestamp": "Oct 12, 2025 · 2:09 AM UTC",
      "url": "https://twitter.com/BTCdayu/status/1977194796071694341#m",
      "author": "BTCdayu"
    },
    {
      "id": "1977171395986825252#m",
      "content": "200多亿美元史诗级爆仓\n机构和代人理财的漏洞没爆多少\n\n两大头部交易所互相看不上眼\nBASE链阴阳币安收费上币\n爆仓的散户让币安给说法\n旁观的散户称币安大格局\n仙界卡灵界的脖子，灵界掐仙界的腰子",
      "timestamp": "Oct 12, 2025 · 12:36 AM UTC",
      "url": "https://twitter.com/BTCdayu/status/1977171395986825252#m",
      "author": "BTCdayu"
    },
    {
      "id": "1977152596298416531#m",
      "content": "没有深夜痛哭者不足以谈人生。\n每个人都经历过非常失败的时刻。\n但是，我们每个人都是一无所有来到这个世界上，所谓失败只不过是短暂的小小考验。\n\n活下来就有机会。",
      "timestamp": "Oct 11, 2025 · 11:21 PM UTC",
      "url": "https://twitter.com/BTCdayu/status/1977152596298416531#m",
      "author": "BTCdayu"
    },
    {
      "id": "1976948148196327587#m",
      "content": "今天坐在电脑前面想了一天\n想讲一个好笑一点的段子\n但失败了，今天根本笑不动了\n就讲一句：BTC 年底20W吧\n希望别是一个笑话。",
      "timestamp": "Oct 11, 2025 · 9:49 AM UTC",
      "url": "https://twitter.com/BTCdayu/status/1976948148196327587#m",
      "author": "BTCdayu"
    },
    {
      "id": "1976874105455755637#m",
      "content": "在修仙的路上，每个人都想要晋升到更高境界\n但这个过程中，无数的人倒在各种意想不到的时候、意想不到的地方。",
      "timestamp": "Oct 11, 2025 · 4:54 AM UTC",
      "url": "https://twitter.com/BTCdayu/status/1976874105455755637#m",
      "author": "BTCdayu"
    },
    {
      "id": "1976858484479344665#m",
      "content": "你卡我脖子，我掐你腰子。",
      "timestamp": "Oct 11, 2025 · 3:52 AM UTC",
      "url": "https://twitter.com/BTCdayu/status/1976858484479344665#m",
      "author": "BTCdayu"
    },
    {
      "id": "1976847127021339011#m",
      "content": "孙哥每次都好神\n这到底是玄学还是又一次巧合……",
      "timestamp": "Oct 11, 2025 · 3:07 AM UTC",
      "url": "https://twitter.com/BTCdayu/status/1976847127021339011#m",
      "author": "BTCdayu"
    },
    {
      "id": "1976844507795845187#m",
      "content": "如果XX跌到多少我就梭哈\n后面真跌到了，不会说话不算话吧？",
      "timestamp": "Oct 11, 2025 · 2:57 AM UTC",
      "url": "https://twitter.com/BTCdayu/status/1976844507795845187#m",
      "author": "BTCdayu"
    },
    {
      "id": "1976827991318778051#m",
      "content": "币圈人起床后心情：\noh shit!\nfuck!\ngod damn!",
      "timestamp": "Oct 11, 2025 · 1:51 AM UTC",
      "url": "https://twitter.com/BTCdayu/status/1976827991318778051#m",
      "author": "BTCdayu"
    },
    {
      "id": "1976797289734918511#m",
      "content": "第一次,BOME热潮后\n下跌200天，比特币跌幅34%\n\n第二次，TRUMP后\n下跌78天见底，跌幅31%，再用3个月回到前高\n\n第三次，BSC MEME热潮\n是否会重演一个小型持续下跌？",
      "timestamp": "Oct 10, 2025 · 11:49 PM UTC",
      "url": "https://twitter.com/BTCdayu/status/1976797289734918511#m",
      "author": "BTCdayu"
    },
    {
      "id": "1976789466212974874#m",
      "content": "早上起来我以为我网络卡了\n现货不怕\n网上看到别人一天的盈亏如图",
      "timestamp": "Oct 10, 2025 · 11:18 PM UTC",
      "url": "https://twitter.com/BTCdayu/status/1976789466212974874#m",
      "author": "BTCdayu"
    },
    {
      "id": "1976533810172027081#m",
      "content": "第八天修仙\n第九天不知道",
      "timestamp": "Oct 10, 2025 · 6:22 AM UTC",
      "url": "https://twitter.com/BTCdayu/status/1976533810172027081#m",
      "author": "BTCdayu"
    },
    {
      "id": "1976482054541017331#m",
      "content": "所以币安要引导一下，聚集到几个好标的上\n无论是哪个我都支持，希望出来30亿的标的。\n我个人目前持有修仙\n中二少年没办法，昨天决定不玩了，但这个还是想再玩一下",
      "timestamp": "Oct 10, 2025 · 2:56 AM UTC",
      "url": "https://twitter.com/BTCdayu/status/1976482054541017331#m",
      "author": "BTCdayu"
    },
    {
      "id": "1976479878607478842#m",
      "content": "meme乱战，必须有一个10亿、30亿的BSC出来，就没人能说什么了\n\n看不上MEME的，PEPE、WIF这些，如今谁敢说个不字？\n\n马斯克的DOGE谁敢说不好？说不好只会被打脸。\n\n所以，除了要公平，其实也可以培育一两个30亿的标的出来。",
      "timestamp": "Oct 10, 2025 · 2:48 AM UTC",
      "url": "https://twitter.com/BTCdayu/status/1976479878607478842#m",
      "author": "BTCdayu"
    },
    {
      "id": "1976478127812641061#m",
      "content": "强大IP能否重燃情绪？走着看吧。",
      "timestamp": "Oct 10, 2025 · 2:41 AM UTC",
      "url": "https://twitter.com/BTCdayu/status/1976478127812641061#m",
      "author": "BTCdayu"
    },
    {
      "id": "1976436876245627074#m",
      "content": "从币的角度修仙\n\n链上内盘射出来，就算炼气\n上了500万，筑基\n上了3000万，结丹\n上了ALPHA，就算元婴，万中选一\n上了现货，那就是化神了",
      "timestamp": "Oct 9, 2025 · 11:57 PM UTC",
      "url": "https://twitter.com/BTCdayu/status/1976436876245627074#m",
      "author": "BTCdayu"
    },
    {
      "id": "1976430454023782878#m",
      "content": "道友讲得也很好。\n\n进入币圈以来的每一天，何尝不是一条修仙路？踩坑、亏损，都是平常事，到处都是陷阱与禁制，有人背靠师门，有人身怀法宝，大多数只能靠苦修与偶然的运气。\n\n大道无情，但天行有常，总有人在这混乱中踏出一条自己的通天大道。",
      "timestamp": "Oct 9, 2025 · 11:31 PM UTC",
      "url": "https://twitter.com/BTCdayu/status/1976430454023782878#m",
      "author": "BTCdayu"
    },
    {
      "id": "1976422576424616309#m",
      "content": "一姐从一个农家小女孩，出社会就是小小杂役弟子，一路也要看尽脸色，刻苦修行，一路经历很多嘲笑、挑战与磨难，终于达成真仙之境。\n\n此文必看！",
      "timestamp": "Oct 9, 2025 · 11:00 PM UTC",
      "url": "https://twitter.com/BTCdayu/status/1976422576424616309#m",
      "author": "BTCdayu"
    },
    {
      "id": "1976421390632055080#m",
      "content": "支持一姐，一起修仙！\n我也想要踏入修仙之旅。\n\n广告1：推荐大家观看B站《凡人修仙传》，男女通杀，绝对是一看就停不下来。\n\n广告2本人修仙小说筹备中，想要角色和特征的评论区留言。",
      "timestamp": "Oct 9, 2025 · 10:55 PM UTC",
      "url": "https://twitter.com/BTCdayu/status/1976421390632055080#m",
      "author": "BTCdayu"
    },
    {
      "id": "1976412706732482619#m",
      "content": "一姐的文章写得很动人。\n\n也顺带强烈推荐大家有空刷一下《凡人修仙传》动漫，B站。1200万人订阅，同时在线卡爆B站，简直是新时代开启的标志。\n\n一声道友尽沧桑，本人的修仙小说也在框架中，大家如果想留名和角色特征，可以在评论区回复，我会纳入笔记，将来合适的时候写上！\n\n写完拍动漫，找币安投资",
      "timestamp": "Oct 9, 2025 · 10:21 PM UTC",
      "url": "https://twitter.com/BTCdayu/status/1976412706732482619#m",
      "author": "BTCdayu"
    },
    {
      "id": "1976297781905195351#m",
      "content": "币安现货以前上一个MEME，10亿是一个大关\n短期情绪就这么多\n现在ALPHA和现货类似，直接用U买卖\n\n那么，上一个是10亿，上4个的话就是大家分，算一下加起来差不多正好10亿。现在继续上10个的话，继续分？如果说当时上palu是意外的惊喜，后面连续再上就是惊吓了。\n\n历史总在重复，高潮过后总是冷清。",
      "timestamp": "Oct 9, 2025 · 2:44 PM UTC",
      "url": "https://twitter.com/BTCdayu/status/1976297781905195351#m",
      "author": "BTCdayu"
    },
    {
      "id": "1976295370629206191#m",
      "content": "投资就是投人\n原来是这么个意思",
      "timestamp": "Oct 9, 2025 · 2:35 PM UTC",
      "url": "https://twitter.com/BTCdayu/status/1976295370629206191#m",
      "author": "BTCdayu"
    },
    {
      "id": "1976293603979972932#m",
      "content": "装逼的人\n杀死逼尔\n牢里的人\n坐牢的人\n那英\n粑粑\n\n巴菲特：我做了90多年投资，目前对大家炒的东西都看不明白。",
      "timestamp": "Oct 9, 2025 · 2:28 PM UTC",
      "url": "https://twitter.com/BTCdayu/status/1976293603979972932#m",
      "author": "BTCdayu"
    },
    {
      "id": "1976281152160923718#m",
      "content": "论投资，打得过巴菲特不多\n但如果让他来币安钱包和我们较量较量\n估计很多伙伴能浇得他落荒而逃",
      "timestamp": "Oct 9, 2025 · 1:38 PM UTC",
      "url": "https://twitter.com/BTCdayu/status/1976281152160923718#m",
      "author": "BTCdayu"
    },
    {
      "id": "1976238558181765306#m",
      "content": "国庆七天人生总结\n\n第一天懵懂\n第二天鄙视\n第三天惊讶\n第四天眼红\n第五天犹豫\n第六天梭哈\n第七天归零\n\n目前已经安心上班。",
      "timestamp": "Oct 9, 2025 · 10:49 AM UTC",
      "url": "https://twitter.com/BTCdayu/status/1976238558181765306#m",
      "author": "BTCdayu"
    },
    {
      "id": "1976194422749761761#m",
      "content": "中秋的币留在中秋\n国秋的币留在国庆\n上班后玩新的？",
      "timestamp": "Oct 9, 2025 · 7:54 AM UTC",
      "url": "https://twitter.com/BTCdayu/status/1976194422749761761#m",
      "author": "BTCdayu"
    },
    {
      "id": "1976190451045515321#m",
      "content": "天天在币圈玩这种几分钟涨上天的游戏\n真的很难适应A股涨10%就涨停的节奏了",
      "timestamp": "Oct 9, 2025 · 7:38 AM UTC",
      "url": "https://twitter.com/BTCdayu/status/1976190451045515321#m",
      "author": "BTCdayu"
    },
    {
      "id": "1976185374100918419#m",
      "content": "直接再翻倍了，太疯狂了。",
      "timestamp": "Oct 9, 2025 · 7:18 AM UTC",
      "url": "https://twitter.com/BTCdayu/status/1976185374100918419#m",
      "author": "BTCdayu"
    },
    {
      "id": "1976182449056158155#m",
      "content": "短短30分钟，一群高手已经落袋这么多了",
      "timestamp": "Oct 9, 2025 · 7:06 AM UTC",
      "url": "https://twitter.com/BTCdayu/status/1976182449056158155#m",
      "author": "BTCdayu"
    },
    {
      "id": "1976181911820124373#m",
      "content": "币安自己的PUMPUFN上第一个跑出来的币\n30分钟最高1.6亿，目前8700万，太猛了\n合约地址只是分享，别买，我也看到太晚了没敢买，5000多万才看到，就买了100U\n\n0x44440f83419de123d7d411187adb9962db017d03\n\n这个币的头像和名字看起来是有备而来，很好奇 是不是一波流直接归零还是保持龙一上ALPHA",
      "timestamp": "Oct 9, 2025 · 7:04 AM UTC",
      "url": "https://twitter.com/BTCdayu/status/1976181911820124373#m",
      "author": "BTCdayu"
    },
    {
      "id": "1976177476289298768#m",
      "content": "太疯狂了，10多分钟 6000万市值\n财富效应甚至远大于预期，大家立即弄起来，打开币安APP，然后APP顶部切换到币安钱包，往里面划转BNB就行了\n\n在其中有一个邀请页面，填邀请码 BTCDAYU 可以省手续费。",
      "timestamp": "Oct 9, 2025 · 6:46 AM UTC",
      "url": "https://twitter.com/BTCdayu/status/1976177476289298768#m",
      "author": "BTCdayu"
    },
    {
      "id": "1976143052566663553#m",
      "content": "这个钱包链接打不开的也可以直接在币安APP中切换到钱包，无私钥钱包，手动填写邀请码BTCdayu就行了\n\n一定记得搞一下，100%概率上面会跑出一个1亿+甚至直接上现货的机会，这是对币安的最优解",
      "timestamp": "Oct 9, 2025 · 4:29 AM UTC",
      "url": "https://twitter.com/BTCdayu/status/1976143052566663553#m",
      "author": "BTCdayu"
    },
    {
      "id": "1976132710218465581#m",
      "content": "大家都要搞一下币安钱包，激活一下\n没填邀请码的填好 btcdayu\n\nweb3.binance.com/referral?re…\n\n币安的新产品听说很快内测，预计从内盘100万市值到1亿市值的肯定多——核心逻辑很简单，太多人会盯着，人一多，资金就活跃\n\n先激活好币安的免私钥钱包，然后放一点BNB等着。",
      "timestamp": "Oct 9, 2025 · 3:48 AM UTC",
      "url": "https://twitter.com/BTCdayu/status/1976132710218465581#m",
      "author": "BTCdayu"
    },
    {
      "id": "1976121863563882990#m",
      "content": "这个应该是外国友人，前来支援币安人生的。",
      "timestamp": "Oct 9, 2025 · 3:05 AM UTC",
      "url": "https://twitter.com/BTCdayu/status/1976121863563882990#m",
      "author": "BTCdayu"
    },
    {
      "id": "1976114759411146943#m",
      "content": "每次高潮的时候，就是低谷的开始\n每次不舍得卖的时候，就是最应该卖的时候\n\n每次都一样，盛宴总在等待有缘的买单人？",
      "timestamp": "Oct 9, 2025 · 2:37 AM UTC",
      "url": "https://twitter.com/BTCdayu/status/1976114759411146943#m",
      "author": "BTCdayu"
    },
    {
      "id": "1976110200903061638#m",
      "content": "孙哥说今天来一波大的\n但他没说什么大的……😂",
      "timestamp": "Oct 9, 2025 · 2:19 AM UTC",
      "url": "https://twitter.com/BTCdayu/status/1976110200903061638#m",
      "author": "BTCdayu"
    },
    {
      "id": "1976077056250348002#m",
      "content": "我炒MEME，但同时也非常敬佩老徐的这种一以贯之的格局：开放心态、产品思维、长线视角等。\n\n下一个10年，最强大的交易场所可能是在链上，现在币安和OKX都在朝这个方向努力，好戏刚刚开场——两边都值得敬畏与尊重。\n\n错过BNB，OKB赋能上再优化下就好了，应该找一个标的去全面赋能，让利。\n@star_okx",
      "timestamp": "Oct 9, 2025 · 12:07 AM UTC",
      "url": "https://twitter.com/BTCdayu/status/1976077056250348002#m",
      "author": "BTCdayu"
    },
    {
      "id": "1975912484755460172#m",
      "content": "太经典，值得收藏\n币圈经典名场面",
      "timestamp": "Oct 8, 2025 · 1:13 PM UTC",
      "url": "https://twitter.com/BTCdayu/status/1975912484755460172#m",
      "author": "BTCdayu"
    },
    {
      "id": "1975875005734154550#m",
      "content": "OKX继续加油。",
      "timestamp": "Oct 8, 2025 · 10:44 AM UTC",
      "url": "https://twitter.com/BTCdayu/status/1975875005734154550#m",
      "author": "BTCdayu"
    },
    {
      "id": "1975869705312444605#m",
      "content": "在BSC热潮中有几类狠人：\n\n1、早早重仓上车的车头\n2、上ALPHA重仓追车的勇士\n3、始终淡定完全不买的高人\n4、很久不上车最后山顶梭哈的莽汉\n5、各种跳车赚钱/亏钱的快枪手\n5、不断打新到处送钱的群演",
      "timestamp": "Oct 8, 2025 · 10:23 AM UTC",
      "url": "https://twitter.com/BTCdayu/status/1975869705312444605#m",
      "author": "BTCdayu"
    },
    {
      "id": "1975862632923140339#m",
      "content": "文章挺长，我帮大家提炼了\n未来5年，底部在800，能涨到4000\n\n五年的话，还真可能不止涨4000。\n现在1300，平均年化30%的话，是4800。\n\n持有BNB才是真正的币安人生，在200多的时候，看不懂币安，这是菜，而菜是原罪……",
      "timestamp": "Oct 8, 2025 · 9:55 AM UTC",
      "url": "https://twitter.com/BTCdayu/status/1975862632923140339#m",
      "author": "BTCdayu"
    },
    {
      "id": "1975848198116974842#m",
      "content": "BNB DATS",
      "timestamp": "Oct 8, 2025 · 8:58 AM UTC",
      "url": "https://twitter.com/BTCdayu/status/1975848198116974842#m",
      "author": "BTCdayu"
    },
    {
      "id": "1975839156648763670#m",
      "content": "有脑就没钱",
      "timestamp": "Oct 8, 2025 · 8:22 AM UTC",
      "url": "https://twitter.com/BTCdayu/status/1975839156648763670#m",
      "author": "BTCdayu"
    },
    {
      "id": "1975790930260336953#m",
      "content": "等国人手上的 $palu\n换手给老外，差不多就要起飞了\n老外能看懂的只有这个\n\n其他各种各样的中文币，他们看的头都要炸掉，就想让我们现在去炒阿拉伯文，一个一个新的阿拉伯项目出来一个字都不认识，你怎么玩？",
      "timestamp": "Oct 8, 2025 · 5:10 AM UTC",
      "url": "https://twitter.com/BTCdayu/status/1975790930260336953#m",
      "author": "BTCdayu"
    },
    {
      "id": "1975751227276165282#m",
      "content": "还好 虚惊一场",
      "timestamp": "Oct 8, 2025 · 2:32 AM UTC",
      "url": "https://twitter.com/BTCdayu/status/1975751227276165282#m",
      "author": "BTCdayu"
    },
    {
      "id": "1975585692865732630#m",
      "content": "明白就好，晚安\npalu",
      "timestamp": "Oct 7, 2025 · 3:35 PM UTC",
      "url": "https://twitter.com/BTCdayu/status/1975585692865732630#m",
      "author": "BTCdayu"
    },
    {
      "id": "1975556160930611239#m",
      "content": "要过币安人生\n没有一个币安吉祥物可不够完美\n$palu",
      "timestamp": "Oct 7, 2025 · 1:37 PM UTC",
      "url": "https://twitter.com/BTCdayu/status/1975556160930611239#m",
      "author": "BTCdayu"
    },
    {
      "id": "1975552577103343888#m",
      "content": "palu这个交易量还是在榜首\n等洗完大概率要起大飞\n筹码极为干净的币安吉祥物\n币安币1000多亿\n这个10多亿也不违和吧？\n持久且唯一的吉祥物，后续出场概率高。",
      "timestamp": "Oct 7, 2025 · 1:23 PM UTC",
      "url": "https://twitter.com/BTCdayu/status/1975552577103343888#m",
      "author": "BTCdayu"
    },
    {
      "id": "1975548404454539471#m",
      "content": "一姐发力“币安人生”，关爱中文用户\nCZ发推“PALU”，面向海外用户",
      "timestamp": "Oct 7, 2025 · 1:06 PM UTC",
      "url": "https://twitter.com/BTCdayu/status/1975548404454539471#m",
      "author": "BTCdayu"
    },
    {
      "id": "1975531644833718495#m",
      "content": "接下来就看\n$PALU 和币安人生哪个后劲足了\n\n我隐隐觉得PALU上现货成为10B的可能性大，但需要时间，需要更多人上车，需要更大的声音。\n\n当然，也可能被打脸，但无妨，币安人生也在车上",
      "timestamp": "Oct 7, 2025 · 12:00 PM UTC",
      "url": "https://twitter.com/BTCdayu/status/1975531644833718495#m",
      "author": "BTCdayu"
    },
    {
      "id": "1975529411375206482#m",
      "content": "今天刷推\n满屏只有两个字：币安",
      "timestamp": "Oct 7, 2025 · 11:51 AM UTC",
      "url": "https://twitter.com/BTCdayu/status/1975529411375206482#m",
      "author": "BTCdayu"
    },
    {
      "id": "1975520594981757385#m",
      "content": "帕鲁说 $4 牛逼，要上现货，我追高买了，被套；\n\n他们又说币安人生创造历史，我割了$4 追币安人生，结果 $PALU 上了\n\n他们说币安人生获利盘太多，我割了币安人生追了 $PALU\n刚进去就暴跌\n\n原来币安人生又上了！？你们的币安人生很爽，我的币安人生好累\n\n——改编微信群段子",
      "timestamp": "Oct 7, 2025 · 11:16 AM UTC",
      "url": "https://twitter.com/BTCdayu/status/1975520594981757385#m",
      "author": "BTCdayu"
    },
    {
      "id": "1975516912517062939#m",
      "content": "这币安人生和欧易人生真的相差这么大？",
      "timestamp": "Oct 7, 2025 · 11:01 AM UTC",
      "url": "https://twitter.com/BTCdayu/status/1975516912517062939#m",
      "author": "BTCdayu"
    },
    {
      "id": "1975516392620474393#m",
      "content": "从ASTER到这一波MEME季，有币安有奇迹。\n不要再挣扎，加入币安人生。\n\n币圈即使遇到干旱，也可以人工降雨。",
      "timestamp": "Oct 7, 2025 · 10:59 AM UTC",
      "url": "https://twitter.com/BTCdayu/status/1975516392620474393#m",
      "author": "BTCdayu"
    },
    {
      "id": "1975510189764977008#m",
      "content": "哪一个会先上现货并冲击10亿市值？",
      "timestamp": "Oct 7, 2025 · 10:35 AM UTC",
      "url": "https://twitter.com/BTCdayu/status/1975510189764977008#m",
      "author": "BTCdayu"
    },
    {
      "id": "1975499789669372140#m",
      "content": "一姐天天活跃在推上\nCZ说自己作为KOL没接过商务\n两个真仙级别的KOL\n别的项目都说重视社区，但他们二位直接就是社区中的一份子……",
      "timestamp": "Oct 7, 2025 · 9:53 AM UTC",
      "url": "https://twitter.com/BTCdayu/status/1975499789669372140#m",
      "author": "BTCdayu"
    },
    {
      "id": "1975440487084614041#m",
      "content": "$PALU 就是泡泡玛特里的Labubu\n\n含金量不用多说\n\n归零到现在拉起来真空区\n\n散户车不重\n\nBNB 破新高\n\n作为第一吉祥物帕鲁的天花板很有想象力\n\n就像ACT上线前几乎没人买\n\n而bn alpha的上线是给大家一次新入场的机会\n\n底部上线，估计至少飞到2-3亿\n\nBsc链这么火热，一直不上alpha也不可能\n\n挑选一个可爱的吉祥物Palu \n\n我觉得是最优解\n\n有文化属性，而且整体来说叙事比较宽泛，中西都比较好理解\n\n#Binance Bsc也有自己的Labubu\n\nLabubu的爆火，直接带飞了泡泡玛特股价\n\n可爱的帕鲁也可能成为Web2和Web3的破圈开始\n\n就如同讨人喜欢的水豚噜噜，奶龙；以及迪士尼的众多IP，玲娜贝儿等等耳熟能详的名字\n\n或许很快能看到帕鲁出演的宣传片\n\n在更大银幕，看到币安的商业版图\n\n就好像迪士尼的世界，梦幻而美妙",
      "timestamp": "Oct 7, 2025 · 5:58 AM UTC",
      "url": "https://twitter.com/BTCdayu/status/1975440487084614041#m",
      "author": "BTCdayu"
    },
    {
      "id": "1975490601438355684#m",
      "content": "今天PALU看到时，在ALPHA只能1万U 1万U这样买\n不过还好钱包里还有一点BNB，直接链上买就快多了\n钱包里放点钱还是有必要的\n另外就是再提醒一下，OKX钱包记得只要使用的，都访问这个网址\nweb3.okx.com/zh-hans/join/dy…\n或输入邀请码dy888\n可以省20%手续费\n\n一切刚刚开始。",
      "timestamp": "Oct 7, 2025 · 9:17 AM UTC",
      "url": "https://twitter.com/BTCdayu/status/1975490601438355684#m",
      "author": "BTCdayu"
    },
    {
      "id": "1975462781563683306#m",
      "content": "国庆放假1号用1百刀买4 \n3号变成685万刀\n然后3号685刀买币安人生\n今天变成68500*600=4后面很多个零的刀\n今天在上ALPHA之前买入PALU\n再获得几十倍涨幅\n\n短短时间，7天用100刀撸一两万亿人民币，一举超越cz，夺得福布斯排行榜第二名\n\n兄弟们赚到扣1",
      "timestamp": "Oct 7, 2025 · 7:26 AM UTC",
      "url": "https://twitter.com/BTCdayu/status/1975462781563683306#m",
      "author": "BTCdayu"
    },
    {
      "id": "1975431129688948750#m",
      "content": "$PALU 就是当年 $ACT 的复刻，这个币，基本上在上线前和ACT一样，只有极少数人有买，当币安上线时，就是给所有人再来一次的机会。\n\n但这个币大概率要比ACT要强，毕竟币安吉祥物太容易让人估值，BNB 1000多亿，吉祥物太有空间了\n\n这一波操作一举多得，可谓神来之笔，肯定是币安中最懂市场的高人决策的，非常牛！币安还是高人多。\n\n几个原因：\n1、给所有人一个底位上车的机会\n币安0风险，因为将来很久以后再怎么跌，二三亿应该还是没啥问题。但币安一两千万上线的，没人能骂，也没人会骂。\n\n2、破局上前上币左右为难的处境\n当前BSC链很热，如果不上ALPHA或接着不停上，或者不上现货，其实都不是最优解，很难办。一直不上吧，社区会骂；不停地上各种吧，币安用户接盘接不过来，最后还是骂。\n\n3、继续强化币安的海内外共识\n直接上一个所有人都没注意，但内在的文化属性很强，持久力OK，海内外共识也容易凝聚的，这就完美破局了。\n\n4、继续壮大链上热度\n这个成为龙头，如果长成到10亿（概念来说确实比4和TST、白布之类都好太多），那链上的活跃度还将继续 ，而BNB也正好借其他势 一道 冲击1500-2000（一姐说2000没问题，肯定要信的）\n\n真的是高明！\n\n最后，我为SOL感觉到悲哀，哈哈。就像 @0xAA_Science 说的，被卡脖子了，不过后面SOL也应该会有破局之道的，但不是现在，现在就是CZ和一姐牛逼，币安牛逼！\n\n所有的奇迹，都发生在币安。",
      "timestamp": "Oct 7, 2025 · 5:20 AM UTC",
      "url": "https://twitter.com/BTCdayu/status/1975431129688948750#m",
      "author": "BTCdayu"
    },
    {
      "id": "1975426981631291580#m",
      "content": "币安这个 $PALU 代币可以直接在币安ALPHA买\n也可以在币安钱包复制合约地址买\n\n当然，也可以用OKX钱包\nweb3.okx.com/join/DY888 【省手续费链接】\n\n币安钱包的邀请链接我得找一下\n\n币安太牛逼了，给所有人一个重新上车的机会！真的是天才的操作——既不能浇灭热情，又不要让用户被浇，太牛。",
      "timestamp": "Oct 7, 2025 · 5:04 AM UTC",
      "url": "https://twitter.com/BTCdayu/status/1975426981631291580#m",
      "author": "BTCdayu"
    },
    {
      "id": "1975425927497834680#m",
      "content": "BSC上最好的MEME来了\n币安的吉祥物\n发推同时上线ALPHA\n时间差不多\n\n真的是币安的仁慈，给所有人一次重新上车的机会\n上线极低市值！！",
      "timestamp": "Oct 7, 2025 · 5:00 AM UTC",
      "url": "https://twitter.com/BTCdayu/status/1975425927497834680#m",
      "author": "BTCdayu"
    },
    {
      "id": "1975424585928790421#m",
      "content": "$4 是2亿，这个是4000万\n这个吉祥物的传播力和持久力不会比4差吧？\n大家觉得呢?\n\n$PALU 是币安的仁慈，给踏空的韭菜的一次机会，要看懂。\n\n还好，老外也能看懂。",
      "timestamp": "Oct 7, 2025 · 4:54 AM UTC",
      "url": "https://twitter.com/BTCdayu/status/1975424585928790421#m",
      "author": "BTCdayu"
    },
    {
      "id": "1975424059619049858#m",
      "content": "教主的功法对很多人应该都是有帮助，有实用性的。\n不过我一开始就只想着将KOL的身份作为学习研究的副产品，我只想站着赚钱，靠研究变现。\n这条路一开始极难，备受嘲笑，尤其是各种失败和打脸，但好在一直是我手写我心，我心成长了，我的收获也就来了。",
      "timestamp": "Oct 7, 2025 · 4:52 AM UTC",
      "url": "https://twitter.com/BTCdayu/status/1975424059619049858#m",
      "author": "BTCdayu"
    },
    {
      "id": "1975421482403827969#m",
      "content": "意料之外，情理之中\n币安没上中文，而是挑了个最低调的PALU！\n币安吉祥物\n当前市值3000多万，超过4的话就是还有6倍\n上现货的话就10亿了。\n0x02e75d28a8aa2a0033b8cf866fcf0bb0e1ee4444",
      "timestamp": "Oct 7, 2025 · 4:42 AM UTC",
      "url": "https://twitter.com/BTCdayu/status/1975421482403827969#m",
      "author": "BTCdayu"
    },
    {
      "id": "1975362282424312111#m",
      "content": "看到一些国外VC投的币圈项目，动不动融资数亿美元，估值几十亿美元，真的纳闷，这真的假的？是不是骗老实人哦。\n\n拿1亿美元，还真的需要投资吗？直接招个团队拿1000万美元做也能做出来吧？",
      "timestamp": "Oct 7, 2025 · 12:47 AM UTC",
      "url": "https://twitter.com/BTCdayu/status/1975362282424312111#m",
      "author": "BTCdayu"
    },
    {
      "id": "1975348841957540293#m",
      "content": "我也投了一个基金一点钱，希望在这样惨淡的时刻，未来反而有一点点超额回报吧。\n\n感觉现在币圈VC反而要少投“币圈”项目，因为币圈内部针对币圈群体的项目，无论要做什么，基本先假定99%都是垃圾就好了。\n\n反而是针对比如连接链下特别注意：加密支付、股票上链、卡牌交易上链等等。",
      "timestamp": "Oct 6, 2025 · 11:53 PM UTC",
      "url": "https://twitter.com/BTCdayu/status/1975348841957540293#m",
      "author": "BTCdayu"
    },
    {
      "id": "1975200807382606256#m",
      "content": "今天\nBTC 12万、ETH 4600、BNB 1220\n\n去年\n6.2万、ETH2400、BNB570\n\n一年100%收益，原来拿着这种大币都可以？震惊。",
      "timestamp": "Oct 6, 2025 · 2:05 PM UTC",
      "url": "https://twitter.com/BTCdayu/status/1975200807382606256#m",
      "author": "BTCdayu"
    },
    {
      "id": "1975197729531068831#m",
      "content": "凡人修仙传中，有一个小绿瓶作为主角外挂存在，后期也圆了来历之类\n如果要你来设计，你会创意一个什么法宝作为陪伴主角成长的灵宝？\n想了很多都不完美，各有不足\n大家有好创意随时反馈我",
      "timestamp": "Oct 6, 2025 · 1:53 PM UTC",
      "url": "https://twitter.com/BTCdayu/status/1975197729531068831#m",
      "author": "BTCdayu"
    },
    {
      "id": "1975196048844054698#m",
      "content": "今天人们在炒作的：\n帕鲁、比心、旺柴、赵长娥、扑街、牛逼、币安勇士、币安牛、佩佩、币安土狗、卧槽、月亮、龙、币安女友、币安人生\n\n真是疯狂的一天，未来是不是会彻底疯狂？",
      "timestamp": "Oct 6, 2025 · 1:46 PM UTC",
      "url": "https://twitter.com/BTCdayu/status/1975196048844054698#m",
      "author": "BTCdayu"
    },
    {
      "id": "1975192498772582851#m",
      "content": "今天的BSC链，给我一种感觉是，接下来两个剧本：\n\n一个是币安上线BSC链MEME\n迎来新一波高潮\n\n一个是迟迟不上，比如一个月，差不多应该就都可以跌90%了，社区开始骂娘。比如不上XXX，BSC就完了。\n\n前者的概率理论上应该更大，尤其是已经上ALPHA的项目。",
      "timestamp": "Oct 6, 2025 · 1:32 PM UTC",
      "url": "https://twitter.com/BTCdayu/status/1975192498772582851#m",
      "author": "BTCdayu"
    },
    {
      "id": "1975190760158040074#m",
      "content": "刷一下推特，看到了很多论述\n币安会上GIGGLE\n币安会上币安人生\n币安会上4\n币安会上龙\n币安会上1\n币安会上其他中文币\n\n当然，我本以为的币安会上 $CARDS ,可以作废了，不会上了应该。\n\n猜不透圣上心思，各人守住自己喜欢的项目就好。",
      "timestamp": "Oct 6, 2025 · 1:25 PM UTC",
      "url": "https://twitter.com/BTCdayu/status/1975190760158040074#m",
      "author": "BTCdayu"
    },
    {
      "id": "1975188707910291789#m",
      "content": "$CARDS 从0.35跌到0.2\n人们在冲中秋快乐之类的东西\n过三个月来回看本条\n\n#投资备忘",
      "timestamp": "Oct 6, 2025 · 1:17 PM UTC",
      "url": "https://twitter.com/BTCdayu/status/1975188707910291789#m",
      "author": "BTCdayu"
    },
    {
      "id": "1975086832036761667#m",
      "content": "炒币，也有价值观。\n有些人，有一些币不炒，有一些事不做。\n但不影响他们在某一些币上赚大钱\n\n本质是念头通达，不能别扭。",
      "timestamp": "Oct 6, 2025 · 6:32 AM UTC",
      "url": "https://twitter.com/BTCdayu/status/1975086832036761667#m",
      "author": "BTCdayu"
    },
    {
      "id": "1975077617821950457#m",
      "content": "hype上现货的深度还是比币安差很大啊？\n前排的BTC、SOL和ETH等，都还是有点不够\n比如对我来说，属于很不好用，在币安可以市价单的仓位，在这里不敢了\n\n不知道未来这种除了用户与交易量的自然增长，还有没有其他方式？",
      "timestamp": "Oct 6, 2025 · 5:56 AM UTC",
      "url": "https://twitter.com/BTCdayu/status/1975077617821950457#m",
      "author": "BTCdayu"
    },
    {
      "id": "1974986343496515939#m",
      "content": "BLUR第一期的时候，都不太看好，结果空投超值钱\n第二期卷上天，结果就和ASTER一样了\nBLAST直接卷麻，应该是人人亏钱了\n\n看来，钱没有凭空产生，只是发生了转移",
      "timestamp": "Oct 5, 2025 · 11:53 PM UTC",
      "url": "https://twitter.com/BTCdayu/status/1974986343496515939#m",
      "author": "BTCdayu"
    },
    {
      "id": "1974978873650802702#m",
      "content": "交易挖矿不产生财富，只是转移财富\n\n这次好像所有人都在挖，我以为是确定的规则下的用劳动力换财富，有很多人要继续暴富。\n\n想不到，仍然是“人挤人的地方没钱捡”。",
      "timestamp": "Oct 5, 2025 · 11:23 PM UTC",
      "url": "https://twitter.com/BTCdayu/status/1974978873650802702#m",
      "author": "BTCdayu"
    },
    {
      "id": "1974966943703789606#m",
      "content": "跟踪一个项目久一点，能学到很多东西\nHYPE从发空投到暴涨，再到30多跌回20\n20时到处是FUD和“理性看空”\n再到JELLY事件，人人喊打，跌回10\n在底部敢买的人没几个\n\n后来，涨回50，每个人都在讨论它、称赞它\n\n而回顾整个过程，所有买入时机都在“大家都不看好的时候”。",
      "timestamp": "Oct 5, 2025 · 10:36 PM UTC",
      "url": "https://twitter.com/BTCdayu/status/1974966943703789606#m",
      "author": "BTCdayu"
    },
    {
      "id": "1974850322536579325#m",
      "content": "想不到后续还有补充规则，挺有意思的，这下干翻hype要再议了",
      "timestamp": "Oct 5, 2025 · 2:53 PM UTC",
      "url": "https://twitter.com/BTCdayu/status/1974850322536579325#m",
      "author": "BTCdayu"
    },
    {
      "id": "1974807890667212823#m",
      "content": "ASTER这发空投的格局很大，直接发，没套路。\n\n发现一个规律：发空投越简单，套路越少的项目，总是越牛B。比如HYPE XPL ASTER之类\n\n而那些各种算计、控筹的，全是垃圾归零项目。\n\n不知道哪个是因，哪个是果，还是互为因果。",
      "timestamp": "Oct 5, 2025 · 12:04 PM UTC",
      "url": "https://twitter.com/BTCdayu/status/1974807890667212823#m",
      "author": "BTCdayu"
    },
    {
      "id": "1974794201662701819#m",
      "content": "很少会和圈外人讨论BTC或投资，因为知道新手“来币圈投资”，大概率是会亏惨的。\n\n但我偶然看到一个新手朋友和亲戚朋友各种人热心推荐炒币，并当起来了炒币的免费老师，超震惊……我能想象，当很快被套牢时，好为人师的新韭菜估计会后悔惨了。\n\n或许都要经过这个？当年我也是这样到处讲BTC的好……",
      "timestamp": "Oct 5, 2025 · 11:10 AM UTC",
      "url": "https://twitter.com/BTCdayu/status/1974794201662701819#m",
      "author": "BTCdayu"
    },
    {
      "id": "1974790064984244381#m",
      "content": "逃顶垃圾币，就像从去往缅北的车上逃跑\n换仓价值币，就像从高铁下车上了滴滴",
      "timestamp": "Oct 5, 2025 · 10:53 AM UTC",
      "url": "https://twitter.com/BTCdayu/status/1974790064984244381#m",
      "author": "BTCdayu"
    },
    {
      "id": "1974779218866376783#m",
      "content": "SOL链被卡脖子这个说法，币圈年度十佳笑点。",
      "timestamp": "Oct 5, 2025 · 10:10 AM UTC",
      "url": "https://twitter.com/BTCdayu/status/1974779218866376783#m",
      "author": "BTCdayu"
    },
    {
      "id": "1974774460973744328#m",
      "content": "记得HYPE早期也很多群友争论，币安会不会上之类\n本质是币圈垃圾项目太多了，只有上币安才有流动性，才能出货。\n\n但真正的好项目，主要还是看项目能赚多少钱，钱多少会给代币赋能\n\n和股票一样，唯一的买家一定要是项目方自己——要有能力和意愿。",
      "timestamp": "Oct 5, 2025 · 9:51 AM UTC",
      "url": "https://twitter.com/BTCdayu/status/1974774460973744328#m",
      "author": "BTCdayu"
    },
    {
      "id": "1974773298098753881#m",
      "content": "坐等韭菜割肉完新高。",
      "timestamp": "Oct 5, 2025 · 9:46 AM UTC",
      "url": "https://twitter.com/BTCdayu/status/1974773298098753881#m",
      "author": "BTCdayu"
    },
    {
      "id": "1974752918881603644#m",
      "content": "这个抽卡普遍反映很上头，一开始就停不下来，总想要去开了卖，开了卖……\n\n赌场生意好，简直是不变的规矩。",
      "timestamp": "Oct 5, 2025 · 8:25 AM UTC",
      "url": "https://twitter.com/BTCdayu/status/1974752918881603644#m",
      "author": "BTCdayu"
    },
    {
      "id": "1974684102877155603#m",
      "content": "好的项目是不需要关心谁喊了，谁关注了\nHYPE谁喊了？JEFF站台了？",
      "timestamp": "Oct 5, 2025 · 3:52 AM UTC",
      "url": "https://twitter.com/BTCdayu/status/1974684102877155603#m",
      "author": "BTCdayu"
    },
    {
      "id": "1974675028806615510#m",
      "content": "很多新手炒MEME，容易觉得龙一太贵了，然后追求龙二、龙三甚至龙九，觉得反正便宜，亏不了多少，结果累积成了大亏。\n\n尤其是容易看别人晒个单就追进去，而大多数时候的龙三、龙四之类，晒单的就是发币的人本尊，进去就是刚好归零。\n\n炒MEME一定要炒龙头，要看交易量。\n亏不了多少和大概率会赚，选一个",
      "timestamp": "Oct 5, 2025 · 3:16 AM UTC",
      "url": "https://twitter.com/BTCdayu/status/1974675028806615510#m",
      "author": "BTCdayu"
    },
    {
      "id": "1974649179965452536#m",
      "content": "很惭愧，一直不做任何广告和商务，否则会有点不知道怎么发推了。",
      "timestamp": "Oct 5, 2025 · 1:33 AM UTC",
      "url": "https://twitter.com/BTCdayu/status/1974649179965452536#m",
      "author": "BTCdayu"
    },
    {
      "id": "1974643532301500567#m",
      "content": "币安将来上线 $cards，会像上线$ordi 一样，点燃整个赛道\n\n这是第1个链接1亿圈外新用户的大赛道。\n\n从商业模式上碾压一切其他rwa——泡泡玛特模式上链，开盲盒的机制天然契合币圈。",
      "timestamp": "Oct 5, 2025 · 1:11 AM UTC",
      "url": "https://twitter.com/BTCdayu/status/1974643532301500567#m",
      "author": "BTCdayu"
    },
    {
      "id": "1974530285833490880#m",
      "content": "Thank you @binance",
      "timestamp": "Oct 4, 2025 · 5:41 PM UTC",
      "url": "https://twitter.com/BTCdayu/status/1974530285833490880#m",
      "author": "BTCdayu"
    },
    {
      "id": "1974307244503359948#m",
      "content": "一个项目，当前每天赚20万美元，一年赚7000万美元\n未来可能一天赚200万美元，一年赚7亿美元\n而其流通市值是4900万美元，FDV是4亿美元。\n\n如果再腰斩，流通市值是2500万美元，假设项目继续平庸经营，则持股者3个月就能回本\n\n持有这种标的，唯一需要做的就是持有，然后每天玩乐放松就好了。",
      "timestamp": "Oct 4, 2025 · 2:55 AM UTC",
      "url": "https://twitter.com/BTCdayu/status/1974307244503359948#m",
      "author": "BTCdayu"
    },
    {
      "id": "1974305807190942203#m",
      "content": "$4 的分歧还是很大，尤其是庄家派：不看好的认为老鼠仓，看好的认为是明牌必上\n\n但在分歧中，其每日交易量分别是\n第一天 6300万\n第二天 1.1亿\n第三天 1.8亿\n交易量与价格走势是重要的观察点。\n\nCZ回来后，币安就像大能的元神归位，莫名就带着强大威压，成为场中的焦点。",
      "timestamp": "Oct 4, 2025 · 2:49 AM UTC",
      "url": "https://twitter.com/BTCdayu/status/1974305807190942203#m",
      "author": "BTCdayu"
    },
    {
      "id": "1974123634655703131#m",
      "content": "meme币的共识是涨出来的\n也只能靠涨出来。",
      "timestamp": "Oct 3, 2025 · 2:45 PM UTC",
      "url": "https://twitter.com/BTCdayu/status/1974123634655703131#m",
      "author": "BTCdayu"
    },
    {
      "id": "1974108529918423121#m",
      "content": "这四个不同级别。",
      "timestamp": "Oct 3, 2025 · 1:45 PM UTC",
      "url": "https://twitter.com/BTCdayu/status/1974108529918423121#m",
      "author": "BTCdayu"
    },
    {
      "id": "1974108160094089283#m",
      "content": "trump高峰700亿，当前70亿。\n那么，cz的4应该是多少？\n骂trump割韭菜的人很多，骂cz大割的基本没有，此战优势在我。",
      "timestamp": "Oct 3, 2025 · 1:43 PM UTC",
      "url": "https://twitter.com/BTCdayu/status/1974108160094089283#m",
      "author": "BTCdayu"
    },
    {
      "id": "1974038450522517836#m",
      "content": "研究了许多代币经济学\n终于明白\n所谓代币经济学\n就是我得到代币，他得到经济",
      "timestamp": "Oct 3, 2025 · 9:06 AM UTC",
      "url": "https://twitter.com/BTCdayu/status/1974038450522517836#m",
      "author": "BTCdayu"
    },
    {
      "id": "1973964406569775458#m",
      "content": "Starting Q4 with 1 BNB hitting 4 ones.\n\nBNB is 4 the culture 💛🖤",
      "timestamp": "Oct 3, 2025 · 4:12 AM UTC",
      "url": "https://twitter.com/BTCdayu/status/1973964406569775458#m",
      "author": "BTCdayu"
    },
    {
      "id": "1973944581319520506#m",
      "content": "有的人说话总是比较偏激。让人感觉他眼中都是坏人。\n\n有的人则行事比较温和，在这类人眼中大多都是好人。\n\n两类人永远都很难做朋友，双方都感觉别扭。",
      "timestamp": "Oct 3, 2025 · 2:53 AM UTC",
      "url": "https://twitter.com/BTCdayu/status/1973944581319520506#m",
      "author": "BTCdayu"
    },
    {
      "id": "1973944173918343418#m",
      "content": "没有主角光环，没有逆天运气，修仙路真的是不容易。\n\n有的人凭天分，有的人靠机缘，有的人靠师门，有的人靠努力，但最终能不能达到更高境界，则是需要诸多因素齐聚，方有望一举突破。\n\n一声道友尽沧桑。",
      "timestamp": "Oct 3, 2025 · 2:52 AM UTC",
      "url": "https://twitter.com/BTCdayu/status/1973944173918343418#m",
      "author": "BTCdayu"
    },
    {
      "id": "1973914816067875059#m",
      "content": "BTC 12万了\n一首《好运来》送给大家\n\n币安昨天上了个100亿的VC币，也上了个4000万的MEME币，双方将要开展有趣的双向奔赴了\n\n项目方、撸毛部队、BNB持有者，舒服了\n散户也舒服，币安这下面面俱到了。\n\nTOM LEE的ETH，CZ的BSC",
      "timestamp": "Oct 3, 2025 · 12:55 AM UTC",
      "url": "https://twitter.com/BTCdayu/status/1973914816067875059#m",
      "author": "BTCdayu"
    },
    {
      "id": "1973704166330823166#m",
      "content": "币安现货会不会上BSC上的MEME？\n会的话，你觉得哪一个概率大？",
      "timestamp": "Oct 2, 2025 · 10:58 AM UTC",
      "url": "https://twitter.com/BTCdayu/status/1973704166330823166#m",
      "author": "BTCdayu"
    },
    {
      "id": "1973666410162536719#m",
      "content": "你以为的比特币巨鲸\n和实际的比特币巨鲸",
      "timestamp": "Oct 2, 2025 · 8:28 AM UTC",
      "url": "https://twitter.com/BTCdayu/status/1973666410162536719#m",
      "author": "BTCdayu"
    },
    {
      "id": "1973650503159656869#m",
      "content": "你的某个较大仓位的币或股票持有时间调查。\n\n越长往往越可能被称之为投资者，越可能是赚钱的",
      "timestamp": "Oct 2, 2025 · 7:25 AM UTC",
      "url": "https://twitter.com/BTCdayu/status/1973650503159656869#m",
      "author": "BTCdayu"
    },
    {
      "id": "1973645015521067235#m",
      "content": "在微信群看到有人发的《凡人修仙传》币圈版，挺好玩的，感觉不是特别准确？\n\n我勉强达到了学徒级别——撸ALPHA分数较低。",
      "timestamp": "Oct 2, 2025 · 7:03 AM UTC",
      "url": "https://twitter.com/BTCdayu/status/1973645015521067235#m",
      "author": "BTCdayu"
    },
    {
      "id": "1973562038891978986#m",
      "content": "让AI比较了一下卡牌和NFT\n\n人数上：TCG> NFT，全球玩家破亿，活跃玩家上千万\n交易额：NFT 高峰期 > TCG，但现在远低于卡牌\n活跃度：短期 NFT 更极端，长期 TCG 更稳定\n\n比“金融化规模/爆发力”，NFT 更大；\n比“人群覆盖、长期文化和稳定性”，TCG 卡牌市场更大。",
      "timestamp": "Oct 2, 2025 · 1:33 AM UTC",
      "url": "https://twitter.com/BTCdayu/status/1973562038891978986#m",
      "author": "BTCdayu"
    },
    {
      "id": "1973554426523820439#m",
      "content": "比特币再涨10倍\n中本聪资产将破万亿美元。",
      "timestamp": "Oct 2, 2025 · 1:03 AM UTC",
      "url": "https://twitter.com/BTCdayu/status/1973554426523820439#m",
      "author": "BTCdayu"
    },
    {
      "id": "1973553410239832145#m",
      "content": "AI的进步让人有点迷茫\n未来，可能人人都要发出疑问\n到底，什么才是真的？",
      "timestamp": "Oct 2, 2025 · 12:59 AM UTC",
      "url": "https://twitter.com/BTCdayu/status/1973553410239832145#m",
      "author": "BTCdayu"
    },
    {
      "id": "1973551795361452444#m",
      "content": "美国很牛很好，但这种在孩子几岁就宣传让他们自由选择性别，提示你虽然有小JJ，但你可能是女孩子，这真是太疯狂，太可恶了。\n\n美国为什么不制订法律，让孩子在成年后自己做决定？而是非要让孩子5岁在学校就不停被暗示？然后在父母不知情的情况下开始变性？\n\n有听说，这是一条非常大的产业链，不知真假",
      "timestamp": "Oct 2, 2025 · 12:53 AM UTC",
      "url": "https://twitter.com/BTCdayu/status/1973551795361452444#m",
      "author": "BTCdayu"
    },
    {
      "id": "1973544683927380133#m",
      "content": "看来要平安着陆了？\n要12万了\n是不是项目方正在卖币买BTC？",
      "timestamp": "Oct 2, 2025 · 12:24 AM UTC",
      "url": "https://twitter.com/BTCdayu/status/1973544683927380133#m",
      "author": "BTCdayu"
    },
    {
      "id": "1973283800311537807#m",
      "content": "问了一下AI，这个卡很贵。",
      "timestamp": "Oct 1, 2025 · 7:08 AM UTC",
      "url": "https://twitter.com/BTCdayu/status/1973283800311537807#m",
      "author": "BTCdayu"
    },
    {
      "id": "1973282733247046143#m",
      "content": "咦，运气有点好？\n第二次抽卡直接抽到一张2000美元的\n……\n我继续抽完这一万U本金，看看怎么样。\n给大家直播完。\nphygitals.com/invite/6e2070",
      "timestamp": "Oct 1, 2025 · 7:04 AM UTC",
      "url": "https://twitter.com/BTCdayu/status/1973282733247046143#m",
      "author": "BTCdayu"
    },
    {
      "id": "1973281787045609634#m",
      "content": "开包中，250U一包，一次买5包\n成本1250\n售出是1066.96\n其中第5张是龙卡，如果是PSA评级品相好，应该是能卖1200-1800美元，看起来这个卡我可以留一下到NFT市场去卖掉了",
      "timestamp": "Oct 1, 2025 · 7:00 AM UTC",
      "url": "https://twitter.com/BTCdayu/status/1973281787045609634#m",
      "author": "BTCdayu"
    },
    {
      "id": "1973276482513543511#m",
      "content": "本文于9月19日发于本人公众号，发出时价格0.2，发出后价格最低至0.1 本人文章无法给出你能不能买，要不要买，买多少，什么价格买，什么价格卖等复杂的问题，请为自己投资负责。",
      "timestamp": "Oct 1, 2025 · 6:39 AM UTC",
      "url": "https://twitter.com/BTCdayu/status/1973276482513543511#m",
      "author": "BTCdayu"
    },
    {
      "id": "1973276375634346082#m",
      "content": "x.com/i/article/197327541075…",
      "timestamp": "Oct 1, 2025 · 6:38 AM UTC",
      "url": "https://twitter.com/BTCdayu/status/1973276375634346082#m",
      "author": "BTCdayu"
    },
    {
      "id": "1973272538135536003#m",
      "content": "币安最近连续上几个RWA项目了，但都是半RWA甚至是假RWA。真RWA，一定是要有大收益，首看商业模式，而对币安来说，用户数最重要的，那链上泡泡玛特没悬念的，100%上。\n\n$CARDS 现在这么点市值，不比现在这些几十亿的空气币好？几十亿上线，对撸ALPHA来说是大毛，但对买币的小散来说体验就很糟糕了。",
      "timestamp": "Oct 1, 2025 · 6:23 AM UTC",
      "url": "https://twitter.com/BTCdayu/status/1973272538135536003#m",
      "author": "BTCdayu"
    },
    {
      "id": "1973234482649113022#m",
      "content": "中国的k签证马上开始，只要有学士学位的国外大学生，理工的几类，就可以来中国工作。\n\n我觉得这是非常好的事情，越多的外来人才经济和科技就越有活力。而且对外开放这件事情也就会变得更加不可逆。\n\n甚至希望将来有一天方便外国友人，就不要再翻墙了吧。",
      "timestamp": "Oct 1, 2025 · 3:52 AM UTC",
      "url": "https://twitter.com/BTCdayu/status/1973234482649113022#m",
      "author": "BTCdayu"
    },
    {
      "id": "1973218515734896877#m",
      "content": "25u一包，回来10到15，给出去的钱理解为买币的。大概刷8000u交易量可以排到前1000个地址，总共14000地址，但有交易量的一半预计。发空投预计10%，这样可以算出大概能拿多少。",
      "timestamp": "Oct 1, 2025 · 2:48 AM UTC",
      "url": "https://twitter.com/BTCdayu/status/1973218515734896877#m",
      "author": "BTCdayu"
    },
    {
      "id": "1973212933099495470#m",
      "content": "教程\n点击左边PACKS，然后选择Pokémon，连接钱包，钱包里有SOL和USDC，就可以抽。\n\n25U一包，抽完会显示市场价多少，然后你可以打个9折卖回去，根据卡不同是11-15U之间，特别稀有的就赚。比如图上这个是10倍收益。\n\n交易额主要用于撸币积分\nphygitals.com/invite/6e2070",
      "timestamp": "Oct 1, 2025 · 2:26 AM UTC",
      "url": "https://twitter.com/BTCdayu/status/1973212933099495470#m",
      "author": "BTCdayu"
    },
    {
      "id": "1973192031821541585#m",
      "content": "《凡人修仙传》在B站创下1200万订阅，简直恐怖。\n刷了一些剧集，很惊喜，动画效果从一开始的低劣，到后来的精良（接近哪吒2视角），配上好的剧本，真的很牛。\n\n不过一些不喜欢的：\n为什么复仇就非要动不动灭门？\n为什么每个修仙者就视凡人如蝼蚁，都是从蝼蚁过来啊\n\n仙侠小说，只有了仙，没有了侠。",
      "timestamp": "Oct 1, 2025 · 1:03 AM UTC",
      "url": "https://twitter.com/BTCdayu/status/1973192031821541585#m",
      "author": "BTCdayu"
    },
    {
      "id": "1973182359890784377#m",
      "content": "VC币行情告一段落\n二级接盘的最傻的资金已套牢\n大盘稍有异动就会大跌\n如果出现抄底良机\n要聚集BTC，聚集有真实收益的项目",
      "timestamp": "Oct 1, 2025 · 12:25 AM UTC",
      "url": "https://twitter.com/BTCdayu/status/1973182359890784377#m",
      "author": "BTCdayu"
    },
    {
      "id": "1973181842552660033#m",
      "content": "RWA的本质仍是生意，生意就要看能赚多少钱\n\nRWA赚钱且发币的，只有 $CARDS ，FDV 3亿多，推荐研究，或许你会感谢我分享了好项目——但短期涨了跌了我不关心，也不讨论。\n\n未发币的可以撸这个，\nphygitals.com/invite/6e2070\n连接钱包，然后SOL链上有USDC就可以，消费PACKS，再卖回去，损耗一次10U左右。",
      "timestamp": "Oct 1, 2025 · 12:23 AM UTC",
      "url": "https://twitter.com/BTCdayu/status/1973181842552660033#m",
      "author": "BTCdayu"
    },
    {
      "id": "1972981157236265245#m",
      "content": "宝可梦卡现在币圈这些项目太火，线下想采购也越来越难了。现在已经发币的这个 $CARD ，因为卡不够，都开不了张，偶尔偷偷开二个小时的抽卡机，立马几千万的交易额，真是很疯狂。\n\n币圈现在有真实收益的优质新项目，就只有三个 $hype $pump $cards ，前两个只要跌得多了，总有人买。第三个等着上币安",
      "timestamp": "Sep 30, 2025 · 11:05 AM UTC",
      "url": "https://twitter.com/BTCdayu/status/1972981157236265245#m",
      "author": "BTCdayu"
    },
    {
      "id": "1972947136196354295#m",
      "content": "从提及时的0.1，快0.2了。\n$CARDS 这个项目一句话解释：链上的泡泡玛特\n\n抽盲盒，抽完是稀有的，大赚；是普通的，平台直接9折回收，平台除了1折的利润，还有交易手续费。\n\n宝可梦卡牌的市场此前是我的盲区，了解后才发现是一个几百亿美元，非常成熟的市场，远比币圈的NFT总规模还大很多。",
      "timestamp": "Sep 30, 2025 · 8:50 AM UTC",
      "url": "https://twitter.com/BTCdayu/status/1972947136196354295#m",
      "author": "BTCdayu"
    },
    {
      "id": "1972896792204439677#m",
      "content": "$XPL=先跑了？",
      "timestamp": "Sep 30, 2025 · 5:30 AM UTC",
      "url": "https://twitter.com/BTCdayu/status/1972896792204439677#m",
      "author": "BTCdayu"
    },
    {
      "id": "1972890878101573732#m",
      "content": "昨天FF上线有关注，结果上来就60亿，不过合约水平太差，没想也没敢去空。\n\n一边是越来越多人在盯开盘，上来就几十亿也认为有合理之处；一边是新币开始走同样的下跌趋势。\n\n从大盘上看，如果BTC跌破100800，可能会开启一段快速的下跌，已经到了博弈的关键点了。",
      "timestamp": "Sep 30, 2025 · 5:06 AM UTC",
      "url": "https://twitter.com/BTCdayu/status/1972890878101573732#m",
      "author": "BTCdayu"
    },
    {
      "id": "1972619293138547035#m",
      "content": "《普通人怎么财富自由？一些简单但有效的建议》\n\n这本来只是一个调侃的贴子，没有想到意外收获巨多的关注。\n也感谢评论区指出比如教会的饭留给需要的人，这些都提示得很对。一方面，许多人都有穷困的时候，理解、支持，不要看不起人；另一方面，每个人可以有向上之心，努力成为更富有的人，有更大能力可以去帮助他人。\n\n作为对上一贴“开玩笑”的“赎罪”，我分享一些普通人如何财富自由的观点——了解我的人应该知道我有这个资格。\n\n因为是临时起意分享一下，所以会写得简单而零碎一些\n\n1、想办法打造管道收入\n无论是撸币安的ALPHA，做自媒体、当项目顾问，写小说等等，一切可以产生“睡后收入”“被动收入”的方式都是好的，如果是程序员还可以比如开发小程序，如果是游戏爱好者，可以去比如ROBOLX等做游戏。\n\n当然，上述这些只是举例，每个人能力不同，兴趣不同，但原则就是你想一想怎么打造你的管道收入。\n\n2、寻找收入的组合拳\n人的时间和精力有限，尽可能让自己每天的时间都是有复利的。\n举个例子：同样是公务员，有的人白天上班忙成狗，下班回家陪老婆带娃，每天重复，时间大量浪费，人没有半点成长，而且随着年龄不断贬值。\n\n但有个叫余华的，在文联工作，上班的主业就是写作，上班写东西是他爱好，下班了也写。回头写东西成功了，出名了，在文联还更有地位，这就是有复利。\n\n3、尽可能让单位时间更有质量\n人一天都只有24小时，24小时的产出有巨大不同。\n你要给自己估计一下，你的一小时值多少钱？我在5年前，就和家人说，我给自己的定价是500元/小时，而且我认为我将来会远超这个收入，所以如果是500元以内可以搞定的事，就不要叫我去了，家人也认可，所以，基本上我可以做自己想做的任何事——比如学习和提升自己。\n\n当然，这里我把自己打游戏的时间也合理化了——人不是机器，也要休息，我打游戏是休息，不能因为我在打游戏就说上面的是错误的。\n\n这个单位时间既指输入要提升，让自己的认知更高。另外也指产出。比如，段永平每天就是打高尔夫，好像天天在玩，但他其实只是把最重要的事情想清楚了，认知提升了，在关键时候的做的一个决策，只需要1秒钟，但这1秒种值的非常钱。黄峥说他基本上不干涉具体的业务，因为他相信下面的人一定比他自己厉害，他“只在必须自己决策的时候才参与”。\n\n所以，我觉得这里是要一些聚集，就是不重要的事情都“差不多就行了”。\n\n4、要抓大趋势\n人一定要在鱼多的地方打渔，把我放在投资圈，我财富自由了。如果我一直在本地的小乡村做一份在当地体面的工作，没有持续的学习，那我肯定也只能守着微薄的收入过活。\n\n我觉得想变得富有，一定要到钱多的地方去。行业上，无非是AI、机器人、新能源、币圈。具体选择上，根据不同的人是从业或投资的区别，选择有所不同。\n\n不过总体来说，都要学一些投资——但一定要找到对的人，普通人往往不能识别真正的投资智慧，但骗子又是主流，实在不行，先从巴菲特学起，是稳妥之策。\n\n我以前工资收入微薄的时候，因为要买房，因为没钱而做了非常多的调研，因为非常多的调研而买到了全城涨幅最离谱的房子，这种开局的运气，给了我一个极大的震撼——原来买个房，就这么简单的一个操作，3年就赚到了我工作20年才能赚到的钱。\n\n投资有风险，但风险=收益，先学习错不了。\n\n5、买点比特币\n这个可能是最简单的方式，相比黄金，还有10倍。现在买可能腰斩，但你无非慢慢买一点，拿10年，等着超越黄金，再涨10倍就行了。\n\n知道一点经济学常识，就知道，美国大印钱是不可避免，法币的通胀不可避免，现在美国一年支付的利息是年收入的1/5，不印钱无解的。\n\n只要印钱，黄金就要涨，比特币就要涨。\n\n就先聊这么一些吧，如果学习一下币圈知识，也可以从 dayu.xyz 开始，虽然好久没更新了，但里面基本也有了从零到亿的智慧了。",
      "timestamp": "Sep 29, 2025 · 11:07 AM UTC",
      "url": "https://twitter.com/BTCdayu/status/1972619293138547035#m",
      "author": "BTCdayu"
    },
    {
      "id": "1972603954111631657#m",
      "content": "币安搞了ASTER，其他交易所的链上合约交易所也在路上了，链上合约取代传统合约的速度会越来越快。\n\n不打算自己做的交易所，还有一个办法就是等熊市直接抄底龙头交易所代币——不过难点就是现在 $HYPE 想等熊市抄底的人太多太多了……能抄到什么样的底没人知道了。",
      "timestamp": "Sep 29, 2025 · 10:06 AM UTC",
      "url": "https://twitter.com/BTCdayu/status/1972603954111631657#m",
      "author": "BTCdayu"
    },
    {
      "id": "1972572770430243211#m",
      "content": "黄金在近25年的走势真是波澜壮阔！\n走势背后是法币的增发。\n\n黄金从约2万亿到25万亿\n用时20年，涨幅10多倍。\n同时期，工资涨幅应该没有这个大——但物价飞涨。\n\n今天，比特币的市值约2万亿出头\n未来，法币将继续以更高速度增发\n\n比特币追赶黄金的路还很长。",
      "timestamp": "Sep 29, 2025 · 8:02 AM UTC",
      "url": "https://twitter.com/BTCdayu/status/1972572770430243211#m",
      "author": "BTCdayu"
    },
    {
      "id": "1972451130413334649#m",
      "content": "香港生活成本，对于许多中产来说，是有不少压力的：\n\n房租：100平，45000\n吃饭：和家人随便出去吃，1000-2000是寻常\n打车：均价150一次算\n教育：如果有小孩子读国际学校，学校不同，一年10-25万/，如果有2个读书就更厉害了\n\n如果换成：住差一些、自己做饭、只地铁、不国际学校，那应该可以省70%",
      "timestamp": "Sep 28, 2025 · 11:59 PM UTC",
      "url": "https://twitter.com/BTCdayu/status/1972451130413334649#m",
      "author": "BTCdayu"
    },
    {
      "id": "1972269746545631566#m",
      "content": "友情转发，文章挺详细的，撸KAITO有用",
      "timestamp": "Sep 28, 2025 · 11:58 AM UTC",
      "url": "https://twitter.com/BTCdayu/status/1972269746545631566#m",
      "author": "BTCdayu"
    },
    {
      "id": "1972269265513545979#m",
      "content": "最近学习到的，如何0元在香港生存：\n\n1、水，不要买8块一瓶的水，地铁站有免费水\n2、吃，许多教会有免费饭\n3、睡，麦当劳24小时营业，长椅可躺，WIFI免费\n4、洗澡，有20多个体育场之类配套干净免费的淋浴间\n\n哈哈，我真没想到原来香港也能0元生存。",
      "timestamp": "Sep 28, 2025 · 11:56 AM UTC",
      "url": "https://twitter.com/BTCdayu/status/1972269265513545979#m",
      "author": "BTCdayu"
    },
    {
      "id": "1972263639257366733#m",
      "content": "“每个人每次看似漂亮的操作背后，都是无数次的血泪和踩坑经验”。\n\n“为了那1%的希望，都要付出100%的努力”。",
      "timestamp": "Sep 28, 2025 · 11:34 AM UTC",
      "url": "https://twitter.com/BTCdayu/status/1972263639257366733#m",
      "author": "BTCdayu"
    },
    {
      "id": "1971910450075099569#m",
      "content": "你是否有通关你的城市？",
      "timestamp": "Sep 27, 2025 · 12:11 PM UTC",
      "url": "https://twitter.com/BTCdayu/status/1971910450075099569#m",
      "author": "BTCdayu"
    },
    {
      "id": "1971849803505209663#m",
      "content": "xpl涨得越多，我就哭得越大声",
      "timestamp": "Sep 27, 2025 · 8:10 AM UTC",
      "url": "https://twitter.com/BTCdayu/status/1971849803505209663#m",
      "author": "BTCdayu"
    },
    {
      "id": "1971818085008240834#m",
      "content": "当前市场的焦点：稳定币、PREPDEX\n下一阶段： $CARDS",
      "timestamp": "Sep 27, 2025 · 6:04 AM UTC",
      "url": "https://twitter.com/BTCdayu/status/1971818085008240834#m",
      "author": "BTCdayu"
    },
    {
      "id": "1971505342011129988#m",
      "content": "希望3个月后，就是昨天的XPL",
      "timestamp": "Sep 26, 2025 · 9:21 AM UTC",
      "url": "https://twitter.com/BTCdayu/status/1971505342011129988#m",
      "author": "BTCdayu"
    },
    {
      "id": "1971505206677619168#m",
      "content": "一个大机会，低付出\n注册这个，连接钱包，去上面抽卡和交易，等发币即可\nphygitals.com/invite/6e2070\n\n可以做5-10个号就够了，CARDS同赛道，目前还没发币\n\n我很看好这个赛道，因为真实收益太高了，CARDS现在是一直按着没开张，只要一开放，24小时销售额瞬间要2000万美元以上，非常可怕——在几乎没人讨论的时候\n\n上面这个零撸就是3个月后今天的XPL，大家都参与一下，这算是我发的唯一一次撸毛\n\n为防合约风险（任何协议都有风险，即使AAVE也不敢说100%），所以大家不要用大资金的钱包，可以搞正常使用的+一些新钱包，而且为了防止被认为是同一个人的地址，将来不给你发币，尽量用一些互相没有转过帐，包括转到交易所地址的，所有的地址模拟 真实的人的行为就好。懒的话就用一个号体验一下也行。\n\n功能很简单，左边最顶上就是首页、市场、抽卡、排行榜、关于\n\n当然，我也买了CARDS代币，等上币安就好了。",
      "timestamp": "Sep 26, 2025 · 9:20 AM UTC",
      "url": "https://twitter.com/BTCdayu/status/1971505206677619168#m",
      "author": "BTCdayu"
    },
    {
      "id": "1971388110056608180#m",
      "content": "现货不怕",
      "timestamp": "Sep 26, 2025 · 1:35 AM UTC",
      "url": "https://twitter.com/BTCdayu/status/1971388110056608180#m",
      "author": "BTCdayu"
    },
    {
      "id": "1971338662186213696#m",
      "content": "大家如果错过 $XPL 又不想追的\n\n可以去OKX存款，直接首页有，支持BTC USDT和OKB，瓜分800万个币，OKX没有海外用户，中文用户多，应该很不卷\n\n高等级省后续费链接\nokx.com/zh-hans/join/dayu888",
      "timestamp": "Sep 25, 2025 · 10:18 PM UTC",
      "url": "https://twitter.com/BTCdayu/status/1971338662186213696#m",
      "author": "BTCdayu"
    },
    {
      "id": "1971337589128065464#m",
      "content": "还好止损了空单，追了现货。\n这个项目的抛压是所有新币中最大的，但是买盘则更是强得过份，一路涨上去\n\n新币第一天交易量对比：\n0G 为6900万\nAVNT 为2亿\nBARD 为1.6亿\n暴涨的ASTER达到3亿\n\n但 $XPL 的交易量15亿？？！！",
      "timestamp": "Sep 25, 2025 · 10:14 PM UTC",
      "url": "https://twitter.com/BTCdayu/status/1971337589128065464#m",
      "author": "BTCdayu"
    },
    {
      "id": "1971253627307295127#m",
      "content": "XPL的盘面太强了吧",
      "timestamp": "Sep 25, 2025 · 4:41 PM UTC",
      "url": "https://twitter.com/BTCdayu/status/1971253627307295127#m",
      "author": "BTCdayu"
    },
    {
      "id": "1971187938940813554#m",
      "content": "赚钱不装逼，等于没赚钱。\n——今日群友提供笑点。",
      "timestamp": "Sep 25, 2025 · 12:20 PM UTC",
      "url": "https://twitter.com/BTCdayu/status/1971187938940813554#m",
      "author": "BTCdayu"
    },
    {
      "id": "1971137750540878333#m",
      "content": "微信上大家都在搜\n中国唯一认可的虚拟币\n\n而答案是数字人民币",
      "timestamp": "Sep 25, 2025 · 9:00 AM UTC",
      "url": "https://twitter.com/BTCdayu/status/1971137750540878333#m",
      "author": "BTCdayu"
    },
    {
      "id": "1971098862095126863#m",
      "content": "我从小就不太会骂人，但是看到推特上有时候有一些人去骂一些我觉得非常非常傻逼的行为的时候，也不禁暗暗笑出了声。",
      "timestamp": "Sep 25, 2025 · 6:26 AM UTC",
      "url": "https://twitter.com/BTCdayu/status/1971098862095126863#m",
      "author": "BTCdayu"
    },
    {
      "id": "1971084952809898030#m",
      "content": "拼多多吞噬世界。\n等这里赚几倍，希望正好赶上科技股崩盘让我上个车。",
      "timestamp": "Sep 25, 2025 · 5:30 AM UTC",
      "url": "https://twitter.com/BTCdayu/status/1971084952809898030#m",
      "author": "BTCdayu"
    },
    {
      "id": "1971073981550940386#m",
      "content": "刷PREP DEX的时候，大家盯着当前价计算收益率，各路人马一起冲，各家DEX一起刷。\n\n既像BLUR第一期意外爆了，第二期卷成马。也像ARB火了之后，大家疯狂开刷四大天王。\n\n预期的场景是：一边刷，一边涨，项目方+工作室+买币的玩家，多方共赢、共贺牛市。\n\n惨烈的场景是：币价跌、积分卷、平台赚。",
      "timestamp": "Sep 25, 2025 · 4:47 AM UTC",
      "url": "https://twitter.com/BTCdayu/status/1971073981550940386#m",
      "author": "BTCdayu"
    },
    {
      "id": "1971052410920686011#m",
      "content": "相当于Google 收购 Coinbase 。\n如果是真的",
      "timestamp": "Sep 25, 2025 · 3:21 AM UTC",
      "url": "https://twitter.com/BTCdayu/status/1971052410920686011#m",
      "author": "BTCdayu"
    },
    {
      "id": "1971017132784959897#m",
      "content": "SBF其实真的很可惜，FTX爆雷后几年后，律师团队从清算款中赚麻了，而用户竟然也得到了赔偿。而这两年下来，SBF投资的各种项目和持仓之类，各种一百倍。\n\n要是FTX没有倒，SBF现在身家应该已经涨了10倍以上了。\n\n可惜没有如果。从庞然大物到被轰然分割，一切发生得太快了，等他出来，这世界早变了模样",
      "timestamp": "Sep 25, 2025 · 1:01 AM UTC",
      "url": "https://twitter.com/BTCdayu/status/1971017132784959897#m",
      "author": "BTCdayu"
    },
    {
      "id": "1970802756664590602#m",
      "content": "保护眼睛的小科普——兼聊iphone唯一不足与“本份”企业文化\n\n一、护眼几大重要参数\n1、PMW调光，重灾区\n很多人在暗光下比如睡前刷手机，而此时如果手机的频闪调节较差的话，会导致眼睛迅速疲劳。\n\nPMW调光如果非常高，则可以减轻闪烁，一般在1800以上，对眼睛就非常友好了。一些对比：\n\nOPPO FIND X8  是3840HZ\nXIAOMI 是1920mhz （低亮度）\niphone 16  是480\n根据身边2位我强制从iphone换为oppo的手机玩家反馈，“真的眼睛舒服太多了”。\n\n好消息是苹果也意识到了这一点，在IPHONE17有所改进，增加了一个关闭“PMW调光功能”，根据官方说明关闭后会降低显示性能——算是一个替代方案。\n\n2、蓝光对视力长期危害，因此各手机都有软件防蓝光，也就是护眼模式，而更进一步的选择是硬件防蓝光，OPPO、小米、荣耀某些型号都有。\n\n这一条看是否通过国际知名护眼认证即可，比如TÜV Rheinland Eye Comfort 4.0\n\n蓝光很多人都有听，只知道有害，但不知道具体有什么危害。\n\n一是眼干、疲劳，尤其晚上，这条都有体会。\n二是造成失眠，会会抑制褪黑激素的分泌，所以这也是为什么睡前刷手机容易越刷越精神，即使是看小说，而同样如果用KINDLE等墨水屏则容易入眼得多。\n三是潜在视网膜损伤。蓝光可以直达视网膜黄斑区域，过度暴露可能造成 光化学损伤，有一定风险老年黄斑变性。\n\n所以，如果使用IPHONE，即使没有硬件防蓝光，也可以24小时将护眼模式打开，稍好一些，而贴上防蓝光膜则可以降低20-40%左右。\n\n不过如果是oppo、小米、华为等有护眼认证的型号，往往是硬件防蓝光，其与上述“开护眼+贴蓝光膜”有本质的区别，即从源头减少了蓝光，而且不影响显示效果，而护眼+膜无法精确减少，只能靠膜的少量“阻隔”，以及护眼模式是在蓝光中混入红与黄的光，降低感受。\n\n二、iphone与OPPO的变化 \n\n在IPHONE4时代，有个朋友问我他比SONY好在哪，我说了一堆它的好，而且都是苹果没宣传的，比如即使是音质芯片这种大多数人没感知的，也是最好的，这样在外接HIFI耳机时能用最高的效果。\n\n所以，那个时候买IPHONE就意味着无脑就选了最好的东西，即使是“柜子背板也是最好的”。\n\noppo与VIVO是段永平一脉出来的，企业文化也将本份与平常心放在很高的地位，不像小米、华为这样出镜率高，但就是扎实做好产品，开线下店（被小米学过去了），然后一步步占领市场。\n\nOPPO看新闻投入了很多钱搞护眼，新款的X9发布会宣传说“熄灯也护眼”，又有一些升级。\n\n当然，小米、华为，尤其是华为，在护眼上应该也做得很好，我有一个华为的平板，MATEPAD AIR 防眩光版，确实做得极好，屏幕质感和阅读纸质类似，用来给家里人刷剧用很不错。\n\n苹果现在的优势就是手机无论怎么做，比如外形有人不满意之类，都不太影响，反而像灵动岛这样的设计，都有国产厂商抄袭，护城河很深，但也希望继续将用户体验做到极致。\n\n如果像微信双开+护眼之类回来了，我也就继续回苹果了，在安全性上，苹果是无敌的。",
      "timestamp": "Sep 24, 2025 · 10:49 AM UTC",
      "url": "https://twitter.com/BTCdayu/status/1970802756664590602#m",
      "author": "BTCdayu"
    },
    {
      "id": "1970793618224161051#m",
      "content": "友情转发支持。\n一句话总结：可能下跌至27，4年后涨至160",
      "timestamp": "Sep 24, 2025 · 10:13 AM UTC",
      "url": "https://twitter.com/BTCdayu/status/1970793618224161051#m",
      "author": "BTCdayu"
    },
    {
      "id": "1970633400706048032#m",
      "content": "以前我很难想象我会使用OPPO的产品\n不过最近已经把全家人的IPHONE、IPAD全换了OPPO系\n原因只有一个护眼无敌了——而我认为这一点很重要，希望能在100岁还能阅读。\n\n而旧的苹果设备则用来做一些重要资料的备份。",
      "timestamp": "Sep 23, 2025 · 11:36 PM UTC",
      "url": "https://twitter.com/BTCdayu/status/1970633400706048032#m",
      "author": "BTCdayu"
    },
    {
      "id": "1970627995619729548#m",
      "content": "巴菲特在世贸大厦被袭击前半年，意识到大规模恐怖主义袭击是“非零概率”，尤其是高层建筑、地标性目标，因此严肃提醒旗下保险公司对相关保险不再续保，但有一家没有放在心上，最终赔付了24亿美元。\n\n最近查理的追思会，马斯克的出场极为亮眼和震奋，他真的是美国甚至是人类的光，各科技大佬出场则极少，也因此，莫名有一些担心，在这样略混乱的地方，出现一个二货要袭击马斯克，也不是“非零概率”，真心希望老马活到150岁。",
      "timestamp": "Sep 23, 2025 · 11:15 PM UTC",
      "url": "https://twitter.com/BTCdayu/status/1970627995619729548#m",
      "author": "BTCdayu"
    },
    {
      "id": "1970440318911947208#m",
      "content": "如果在2000年股灾持有伟大公司亚马逊十年\n那么收获95%跌幅,从5跌至0.5以下\n坚持价值投资,死拿10年,终于获得了可观涨幅到7\n\n而如果另一个是08年进场,也拿十年\n他会收获2到100的50部\n\n同样是人生中美好的十年,同一个标的,不同的人生",
      "timestamp": "Sep 23, 2025 · 10:49 AM UTC",
      "url": "https://twitter.com/BTCdayu/status/1970440318911947208#m",
      "author": "BTCdayu"
    },
    {
      "id": "1970432699908403292#m",
      "content": "最近在 $YZY $ASTER  $0G 上皆有所斩获，主要还是运气不错。目前，大众普遍看好PREP DEX，但反而不一定能成为大机会了。\n\n目前观察到的二三个大机会很可能在链上，在OKX钱包提前放好前吧，多分一些地址等着。\n\n每个地址一定要绑一个省手续费链接，确保均访问过。\n\n好运链接\nweb3.okx.com/zh-hans/join/dy…",
      "timestamp": "Sep 23, 2025 · 10:18 AM UTC",
      "url": "https://twitter.com/BTCdayu/status/1970432699908403292#m",
      "author": "BTCdayu"
    }
  ],
  "meta": {
    "capturedAt": "2025-10-21T00:07:15.531Z",
    "tweetLimit": 200,
    "tweetsFetched": 200,
    "pagesFetched": 11,
    "sourceFile": "twitter-Following-1760964620895.json",
    "durationMs": 25385,
    "cursorTrail": [
      "DAAHCgABG3vigmS__-oLAAIAAAATMTk3OTA3MjA3MDIzMjQ1NzM3OAgAAwAAAAIAAA",
      "DAAHCgABG3vigmS__9YLAAIAAAATMTk3NzYxMjAzMzA2MDQyMTkyNAgAAwAAAAIAAA",
      "DAAHCgABG3vigmS__8ELAAIAAAATMTk3NjQ3ODEyNzgxMjY0MTA2MQgAAwAAAAIAAA",
      "DAAHCgABG3vigmS__6wLAAIAAAATMTk3NjExNDc1OTQxMTE0Njk0MwgAAwAAAAIAAA",
      "DAAHCgABG3vigmS__5kLAAIAAAATMTk3NTUxNjkxMjUxNzA2MjkzOQgAAwAAAAIAAA",
      "DAAHCgABG3vigmS__4QLAAIAAAATMTk3NTE4ODcwNzkxMDI5MTc4OQgAAwAAAAIAAA",
      "DAAHCgABG3vigmS__28LAAIAAAATMTk3NDMwNTgwNzE5MDk0MjIwMwgAAwAAAAIAAA",
      "DAAHCgABG3vigmS__1oLAAIAAAATMTk3MzI4MTc4NzA0NTYwOTYzNAgAAwAAAAIAAA",
      "DAAHCgABG3vigmS__0ULAAIAAAATMTk3MjI2OTI2NTUxMzU0NTk3OQgAAwAAAAIAAA",
      "DAAHCgABG3vigmS__zALAAIAAAATMTk3MDYzMzQwMDcwNjA0ODAzMggAAwAAAAIAAA"
    ],
    "attempts": 1,
    "skipped": false
  }
}